Workbook

Sheet Model Guide
B1: MICRON TECHNOLOGY ($MU) — MODEL GUIDE
B3: HOW TO READ THIS MODEL
B5: Color Convention | C5: Meaning | D5: Example
B6: Blue font | C6: Hardcoded input — a number you can change | D6: Revenue: $23,860M
B7: Black font | C7: Formula — calculated from other cells, do not edit | D7: Gross Profit = Revenue - COGS
B8: Green font | C8: Cross-sheet link — pulls data from another tab | D8: =Assumptions!B55 -> 8710
B9: Yellow highlight | C9: Key assumption — the inputs that matter most | D9: Gross Margin: 81%
B11: HOW THE MODEL FLOWS
B13: Step | C13: What Happens | D13: Where to Look
B14: 1. Assumptions | C14: All inputs live here. Change any blue number and the entire model updates. Revenue, margins, pricing, capex, shares, scenarios — everything starts here. | D14: Assumptions tab, rows 7-48 (inputs), rows 55-72 (calculated outputs)
B16: 2. Revenue Build | C16: Revenue is built from: Total Revenue x DRAM% = DRAM Revenue. DRAM x HBM% = HBM Revenue. Remainder = NAND. This shows WHERE revenue comes from. | D16: Assumptions rows 55-62. Also see Supply Model (fab capacity) and Bit Economics (wafer-level math).
B18: 3. Income Statement | C18: Historical actuals (6 quarters) and projected estimates (6 quarters) flow from Assumptions. Revenue - COGS = Gross Profit. GP - OpEx = Operating Income. OI - Tax = Net Income. NI / Shares = EPS. | D18: Historical P&L (actuals) and Projected P&L (forecasts). All green-font cells trace back to Assumptions.
B20: 4. Balance Sheet | C20: Tracks cash, debt, inventory, PP&E over time. The key story: Micron went from net debt to $6.6B net cash in 3 quarters while spending $25B+ on capex. | D20: Balance Sheet & CF tab. Cash flow section shows OCF, CapEx, FCF, buybacks, dividends, debt paydown.
B22: 5. Valuation | C22: Multiple methods to answer: what is the stock worth? P/E multiples, DCF, EV/EBITDA, FCF yield, sum-of-parts. Each gives a different answer — the range IS the answer. | D22: Valuation tab (7 methods + sensitivity table), DCF tab (full discounted cash flow), ROIC Analysis (return on capital).
B24: 6. Thesis | C24: Everything synthesizes into: BUY or SHORT? At what conviction? What are the risks? What would change our mind? | D24: Thesis Summary tab. Also Risks & Catalysts for what could go wrong/right.
B27: TAB-BY-TAB GUIDE
B29: Tab | C29: What It Contains | D29: What to Look For
B30: Assumptions | C30: The control panel. Every input that drives the model: DRAM/NAND pricing growth rates, gross margin, R&D/SG&A as % of revenue, capex, buybacks, dividends, shares outstanding, tax rate. Also 4 valuation scenarios with probabilities, P/E multiples, and EPS paths. Rows 55-72 show the formulas that convert inputs into revenue, profits, and EPS. | D30: Row 47: Probability-weighted target price. Row 48: Implied upside/downside. Change ANY blue number and watch these update. Row 68: Quarterly EPS (the most important output).
B31: Historical P&L | C31: Actual income statement for FQ1-25 through FQ2-26 (6 quarters) plus FY annual columns. Revenue split into DRAM/NAND. Gross profit, operating income, net income, EPS. Business unit revenue and margins at the bottom. | D31: Row 18: Gross margin trend (39.5% to 75.0% in 6 quarters — the supercycle in one number). Row 35: Non-GAAP EPS ($1.79 to $12.20). Row 38: HBM revenue estimates. Rows 49-55: BU margins show MCBU at 79% GM — highest in the company.
B32: Projected P&L | C32: Forward income statement for FQ3-26E through FQ4-27E (6 projected quarters). All driven by Assumptions tab. FQ3-26E is guided: $33.5B revenue, 81% GM, $19.15 EPS. FY annual columns sum the quarters. | D32: Row 8: $33.5B single quarter exceeds entire FY2024 ($25.1B). Row 33: EPS path — $19.15 guided for FQ3, then normalization. Rows 37-40: Key forecast observations.
B33: Balance Sheet & CF | C33: Balance sheet at 4 time points plus 2 projected. Cash flow statement showing OCF, capex, FCF. Capital return: buybacks (CHIPS Act-capped), dividends (30% increase), debt paydown ($4.37B in H1-FY26). | D33: Row 19: Net Debt/(Net Cash) — Micron crossed to net cash. Row 25: Free cash flow ($6.9B record in FQ2-26, guided to 'roughly double' in FQ3). Row 35: FY2026 capex >$25B.
B34: Supply Model | C34: Physical fab map (10 fabs by geography/node/capacity). Node transition timeline (1-alpha through 1-delta). HBM wafer trade ratios. Industry supply/demand balance. Micron strategic shifts (Crucial exit, stacked GDDR, HBM4). SemiAnalysis key findings. HBM market share. New capacity timeline through 2030. | D34: Row 44: Supply/demand spread — negative means tight (prices rise). Rows 55-67: SemiAnalysis data (once-in-40yr shortage, memory = 30% of hyperscaler capex). Rows 71-73: HBM share — SK Hynix 62%, Micron 21%, Samsung 17%. Rows 77-83: No new capacity until 2027-2028.
B35: Bit Economics | C35: Bottom-up revenue decomposition: wafer starts x bits/wafer = output. HBM cannibalization (each HBM wafer removes 3-5x commodity DRAM supply). ASP/cost spread (THE margin driver). Yield curves by node. HBM stack unit P&L (cost, ASP, margin per stack). Revenue per wafer comparison. | D35: Row 19: ASP/Cost Spread — above 2.0x = strong margins, below 1.0x = losses. Currently unprecedented. Rows 54-70: HBM stack economics show HBM4 at ~$1,800/stack ASP. Row 74: HBM4 generates 10x revenue per wafer vs commodity DDR5.
B36: HBM Contracts | C36: HBM TAM trajectory ($35B to $100B by 2028). Customer map (6 customers). Long-term supply agreements across industry. Contract structure types. Revenue lock-in estimate (~78%). 5-year SCA details. Post-settlement pricing model. Vera Rubin HBM4 allocation. OpenAI/Stargate deal. | D36: Row 8: Micron HBM revenue trajectory. Rows 30-34: Industry LTA map — MS/Google signing 3-5yr deals with ALL memory makers. Row 55: Vera Rubin — Micron EXCLUDED from flagship (key risk). Row 77: ~78% of forward revenue is locked in. Row 92-94: Post-settlement pricing means Micron captures 100% of price upside.
B37: Debt Schedule | C37: Individual debt tranches (9 instruments with coupons/maturities). Maturity wall. Interest expense build by tranche. Coverage ratios (EBITDA/interest). Refinancing risk assessment. Net debt trajectory to FY2028. | D37: Row 16: $10.1B total debt (down from $14.6B). Row 30: Net cash trajectory — heading to deep net cash by FY2028. Row 57: Quarterly interest only ~$100M (immaterial vs $30B+ revenue). Row 61: Interest coverage >200x (essentially no credit risk).
B38: Working Capital | C38: Inventory decomposition (raw materials, WIP, finished goods). Days Inventory Outstanding — THE leading indicator of cycle turns. Cash Conversion Cycle. Historical DIO context table. Working capital intensity. | D38: Row 14: DIO — below 120 days = very tight (bullish). Above 140 = building (bearish). Currently ~123 days = strong demand pull. Rows 36-40: DIO cycle context table — tells you where we are in the memory cycle. Row 32: Cash Conversion Cycle.
B39: Share Count Bridge | C39: Basic shares + dilution (RSUs/options) - buybacks = diluted shares. Treasury stock method detail. RSU vesting schedule. Buyback capacity analysis. EPS sensitivity to share count. | D39: Row 9: Buyback acceleration post-Dec 2026 when CHIPS restrictions ease — shares retired jump from ~1M/qtr to 6-7M/qtr. Row 11: Diluted shares peak at 1,148M (FQ4-26E) then decline to 1,105M (FQ4-27E). Row 43: EPS sensitivity — every 10M shares = ~$0.40 EPS difference.
B40: DCF | C40: Full discounted cash flow model. WACC build (CAPM). 6-year explicit FCF projections. Terminal value (Gordon Growth). Enterprise-to-equity bridge. Sensitivity table (WACC vs terminal growth). Scenario DCFs. FCFE vs FCFF reconciliation. Football field summary. Beating the Tide $934 PT comparison. | D40: Row 14: WACC (~10.9%). Row 31: Unlevered FCF by year. Row 53: DCF fair value per share (~$520 base case). Rows 58-65: Sensitivity table — green cells are above current price, red below. Row 73: Probability-weighted DCF ~$490. Rows 89-97: Football field — 7 methods showing Low/Base/High range.
... B45: Thesis Summary | C45: The 2-minute executive summary. BUY/SHORT recommendation. Probability-weighted target price and upside. Variant perception (where we differ from consensus). 4 scenario descriptions. Capital return status. Monitoring signals (upgrade/cut triggers). Latest intelligence. | D45: Row 3: The answer — BUY, HIGH CONVICTION. Row 4-5: Target and upside. Rows 8-10: Variant perception — this is where the ALPHA comes from. Rows 28-37: What would make us upgrade or cut the position.
B48: SLIDE DECK MAP
B49: Use this to build your pitch deck. Each slide maps to specific model sections.
B51: Slide | C51: What Goes On It | D51: Pull Data From
B52: 1. Company Overview | C52: What Micron does: #3 global memory maker (DRAM + NAND + HBM). Key stats: $106B FY26E revenue, 1,142M shares, $366 stock price. Market position: oligopoly (Samsung 38%, SK Hynix 33%, Micron 23% DRAM share). | D52: Comps tab rows 5-13. Assumptions row 55 (revenue). Thesis Summary row 3.
B53: 2. Industry Overview | C53: Memory industry structure: DRAM oligopoly, NAND more fragmented. AI driving structural shift: HBM TAM $35B (CY25) to $100B (CY28). Memory = 30% of hyperscaler capex (was 8% in CY23). Once-in-40-year shortage per SemiAnalysis. | D53: Supply Model rows 40-44 (S/D balance), 55-67 (SemiAnalysis data). HBM Contracts rows 4-8 (TAM). Comps rows 16-24 (tech positioning).
B54: 3. Investment Thesis | C54: BUY at $366. Probability-weighted target ~$554 (51% upside). 3 variant perceptions: (1) supply constraint duration, (2) revenue quality transformation, (3) deleveraging pace. Key stat: FQ3-26E single quarter = $33.5B > entire FY2024. | D54: Thesis Summary rows 3-10. Assumptions rows 47-48 (target/upside). Projected P&L row 8 (FQ3 guide).
B55: 4. Revenue Deep Dive | C55: Revenue decomposition: DRAM 79%, NAND 21%. HBM ~32% of DRAM and growing. Revenue by BU: CMBU 32%, MCBU 32%, CDBU 24%, AEBU 11%. Revenue QoQ: +75% in FQ2-26. Crucial consumer exit redirecting capacity to AI. | D55: Historical P&L rows 8-13, 43-47. Bit Economics rows 4-24 (bit-level decomposition). HBM Contracts rows 10-18 (customer map).
B56: 5. Margin Analysis | C56: Gross margin: 39.5% to 75.0% in 6 quarters (to 81% guided). Why: ASP/cost spread at historic high. ASP +65% QoQ while cost/bit declining 7%. Structural argument: 5 reasons margins stay higher (from CFO Murphy). | D56: Assumptions row 15 (GM trend). Historical P&L row 18 (GM), rows 49-55 (BU margins). Bit Economics row 19 (ASP/cost spread). Working Capital rows 14, 36-40 (DIO cycle context).
B57: 6. HBM & Contracts | C57: HBM: the game-changer. 100% of CY2026 committed. First 5-year SCA signed. ~78% of revenue locked in. Industry shifting from spot to contracted: price floors, prepayments, take-or-pay. Post-settlement pricing captures 100% upside. | D57: HBM Contracts (entire tab). Key rows: 8 (revenue), 30-34 (industry LTAs), 63-69 (contract types), 77 (lock-in estimate), 81-89 (SCA details).
B58: 7. Valuation | C58: 7 methodologies all pointing to $450-550 range. DCF: ~$520 base case. P/E: 12x on $48 FY27 consensus = $576. Football field: $250-$760 range. Sensitivity table: color-coded grid. Consensus: 38 Buy / 0 Sell, avg PT $492. | D58: Valuation tab rows 13-20, 24-29, 37-46. DCF tab rows 53, 73, 89-97. Assumptions rows 47-48.
B59: 8. Capital Allocation | C59: CapEx: $25B+ FY26 (rising to $35B+ FY27). CHIPS Act: $6.4B in grants. Buybacks: capped by CHIPS until Dec 2026, then acceleration to ~$10B/yr. Dividend: 30% increase. Debt: $4.37B paid down in H1-FY26. Net cash: $6.6B. | D59: Assumptions rows 22-26. Balance Sheet & CF rows 23-31. Share Count Bridge rows 6-11, 16-22. Debt Schedule rows 16, 30.
B60: 9. Risks & Catalysts | C60: Top risks: Vera Rubin HBM4 exclusion (60% prob), TurboQuant (20% but 2028+), hyperscaler capex cliff (15%), tariffs (30% but largely exempt). Catalysts: FQ3 earnings (Jun 26), CHIPS buyback easing (Dec 26), Samsung/Google LTAs. | D60: Risks & Catalysts (entire tab). Key rows: 5-12 (risk matrix), 17-27 (catalyst calendar), 47-51 (critical new risks). Supply Model rows 55-73 (HBM share allocation).
B61: 10. Scenario Analysis | C61: 4 scenarios: Bull ($960), Base ($576), Bear ($240), Hard Landing ($72). Probability-weighted: ~$554. Each scenario has distinct EPS path, margin trajectory, and appropriate P/E multiple. BofA models FY28 EPS declining to $29 = explicit cycle downturn. | D61: Assumptions rows 30-45. Valuation rows 24-29. DCF rows 69-73 (scenario DCFs). ROIC Analysis rows 44-45 (incremental ROIC shows cycle norm is expected).
B63: QUICK REFERENCE — KEY NUMBERS
B65: Metric | C65: Value | D65: Context
B66: Stock Price | C66: $366 | D66: Post-22% sell-off from $471 ATH
B67: FQ2-26 Revenue | C67: $23.86B | D67: +196% YoY, 4th consecutive record
B68: FQ3-26E Revenue (guided) | C68: $33.5B | D68: Single quarter > entire FY2024
B69: FQ2-26 Gross Margin | C69: 75.0% | D69: FQ3-26E guided to 81%
B70: FQ2-26 EPS (non-GAAP) | C70: $12.20 | D70: Beat consensus $9.31 by 31%
B71: FY2026E Revenue | C71: ~$106B | D71: +183% YoY
B72: FY2027E EPS (consensus) | C72: $48.07 | D72: Range: $28-$80
B73: Prob-Weighted Target | C73: ~$554 | D73: 51% upside to current
B74: Analyst Consensus | C74: 38 Buy / 0 Sell | D74: Avg PT: $492
B75: HBM TAM (CY2028) | C75: $100B | D75: Pulled forward 2 years
B76: Revenue Lock-In | C76: ~78% | D76: Contracted + committed
B77: DRAM Undersupply (CY2026) | C77: 4.9% | D77: Worst in 15+ years per Goldman
B79: Model as of April 5, 2026. All data from public SEC filings, management disclosures, and third-party research.
B80: Sources: Micron 10-Q/10-K, earnings call transcripts, TrendForce, SemiAnalysis, Goldman Sachs, analyst reports.
B81: NOT INVESTMENT ADVICE. FOR ANALYTICAL AND EDUCATIONAL PURPOSES ONLY.

Sheet Assumptions
A1: MICRON TECHNOLOGY ($MU) — INVESTMENT MODEL ASSUMPTIONS
A2: As of April 5, 2026 | Fiscal Year Ends Late August | H2: Blue = hardcoded input | J2: Black = formula | L2: Green = cross-sheet link | N2: Yellow highlight = key assumption
B4: FQ1-25 | C4: FQ2-25 | D4: FQ3-25 | E4: FQ4-25 | F4: FQ1-26 | G4: FQ2-26 | H4: FQ3-26E | I4: FQ4-26E | J4: FQ1-27E | K4: FQ2-27E | L4: FQ3-27E | M4: FQ4-27E
B5: A | C5: A | D5: A | E5: A | F5: A | G5: A | H5: E | I5: E | J5: E | K5: E | L5: E | M5: E
A7: REVENUE & PRICING ASSUMPTIONS
A8: DRAM ASP Change QoQ (%) | B8: 0.1 | C8: 0.05 | D8: 0.15 | E8: 0.25 | F8: 0.4 | G8: 0.65 | H8: 0.4 | I8: 0.2 | J8: 0.08 | K8: 0.05 | L8: 0.03 | M8: 0
A9: NAND ASP Change QoQ (%) | B9: 0.05 | C9: 0.03 | D9: 0.1 | E9: 0.12 | F9: 0.3 | G9: 0.78 | H9: 0.45 | I9: 0.15 | J9: 0.05 | K9: 0.03 | L9: 0 | M9: -0.03
A10: DRAM % of Total Revenue | B10: 0.73 | C10: 0.76 | D10: 0.76 | E10: 0.8 | F10: 0.79 | G10: 0.79 | H10: 0.8 | I10: 0.8 | J10: 0.79 | K10: 0.79 | L10: 0.78 | M10: 0.78
A11: HBM ASP Premium (x) | B11: 5 | C11: 5.2 | D11: 5.5 | E11: 5.8 | F11: 6 | G11: 6.2 | H11: 6 | I11: 5.5 | J11: 5 | K11: 4.5 | L11: 4.2 | M11: 4
A12: HBM % of DRAM Revenue | B12: 0.12 | C12: 0.15 | D12: 0.18 | E12: 0.22 | F12: 0.28 | G12: 0.32 | H12: 0.35 | I12: 0.38 | J12: 0.4 | K12: 0.42 | L12: 0.43 | M12: 0.44
A13: Samsung DRAM Pricing (ref) | B13: N/A | C13: N/A | D13: N/A | E13: N/A | F13: 1 | G13: 2 | H13: 2.6 | I13: 3
A14: COST & MARGIN ASSUMPTIONS
A15: Gross Margin (%) | B15: 0.395 | C15: 0.368 | D15: 0.377 | E15: 0.447 | F15: 0.568 | G15: 0.75 | H15: 0.81 | I15: 0.78 | J15: 0.72 | K15: 0.68 | L15: 0.65 | M15: 0.63
A16: DRAM Cost/Bit Decline QoQ | B16: -0.04 | C16: -0.04 | D16: -0.05 | E16: -0.06 | F16: -0.07 | G16: -0.07 | H16: -0.06 | I16: -0.05 | J16: -0.05 | K16: -0.04 | L16: -0.04 | M16: -0.03
A17: R&D as % of Revenue | B17: 0.115 | C17: 0.12 | D17: 0.11 | E17: 0.095 | F17: 0.085 | G17: 0.055 | H17: 0.045 | I17: 0.048 | J17: 0.055 | K17: 0.058 | L17: 0.06 | M17: 0.062
A18: SG&A as % of Revenue | B18: 0.04 | C18: 0.042 | D18: 0.038 | E18: 0.032 | F18: 0.028 | G18: 0.02 | H18: 0.018 | I18: 0.02 | J18: 0.025 | K18: 0.027 | L18: 0.028 | M18: 0.03
A19: Effective Tax Rate | B19: 0.115 | C19: 0.115 | D19: 0.115 | E19: 0.115 | F19: 0.151 | G19: 0.151 | H19: 0.151 | I19: 0.151 | J19: 0.151 | K19: 0.151 | L19: 0.151 | M19: 0.151
A21: CAPEX & CAPITAL ALLOCATION
A22: Gross CapEx ($B) | B22: 3.1 | C22: 3.3 | D22: 3.5 | E22: 3.8 | F22: 4.5 | G22: 5 | H22: 7 | I22: 8.5 | J22: 9 | K22: 9.5 | L22: 10 | M22: 10.5
A23: CHIPS Act Grant Offsets ($B) | B23: 0.3 | C23: 0.3 | D23: 0.3 | E23: 0.3 | F23: 0.3 | G23: 0.3 | H23: 0.3 | I23: 0.3 | J23: 0.3 | K23: 0.3 | L23: 0.3 | M23: 0.3
A24: Share Buybacks ($M) | B24: 0 | C24: 0 | D24: 0 | E24: 0 | F24: 300 | G24: 350 | H24: 350 | I24: 350 | J24: 1500 | K24: 2500 | L24: 3000 | M24: 3000
A25: Dividend per Share ($) | B25: 0.115 | C25: 0.115 | D25: 0.115 | E25: 0.115 | F25: 0.115 | G25: 0.15 | H25: 0.15 | I25: 0.15 | J25: 0.175 | K25: 0.175 | L25: 0.175 | M25: 0.175
A26: Diluted Shares Outstanding (M) | B26: 1118 | C26: 1120 | D26: 1125 | E26: 1131 | F26: 1138 | G26: 1142 | H26: 1145 | I26: 1148 | J26: 1140 | K26: 1130 | L26: 1118 | M26: 1105
A28: VALUATION & SCENARIO ASSUMPTIONS
A29: Current Share Price ($) | B29: 366
A30: Scenario: AI Supercycle (Bull) | B30: 0.25
A31: Scenario: Steady Growth (Base) | B31: 0.45
A32: Scenario: Cyclical Correction (Bear) | B32: 0.2
A33: Scenario: Hard Landing | B33: 0.1
A34: Probability Sum (must = 100%) | B34: =SUM(B30:B33) -> 1
A36: P/E Multiple: AI Supercycle | B36: 16
A37: P/E Multiple: Steady Growth | B37: 12
A38: P/E Multiple: Cyclical Correction | B38: 8
A39: P/E Multiple: Hard Landing | B39: 6
A41: SCENARIO EPS PATHS (FY2027E NTM EPS)
A42: FY2027E EPS: AI Supercycle | B42: 60
A43: FY2027E EPS: Steady Growth | B43: 48
A44: FY2027E EPS: Cyclical Correction | B44: 30
A45: FY2027E EPS: Hard Landing | B45: 12
A47: PROBABILITY-WEIGHTED TARGET PRICE | B47: =B30*B42*B36 + B31*B43*B37 + B32*B44*B38 + B33*B45*B39 -> 554.4
A48: Implied Upside / (Downside) to Current | B48: =(B47-B29)/B29 -> 0.5147541
A49: REFERENCE NOTES
A50: Tariff Impact | B50: -0.005
A51: Circular References | B51: None
A52: Bit Shipment Data | B52: In comment
A54: QUARTERLY REVENUE ($M) | B54: FQ1-25 | C54: FQ2-25 | D54: FQ3-25 | E54: FQ4-25 | F54: FQ1-26 | G54: FQ2-26 | H54: FQ3-26E | I54: FQ4-26E | J54: FQ1-27E | K54: FQ2-27E | L54: FQ3-27E | M54: FQ4-27E
A55: Total Revenue | B55: 8710 | C55: 8053 | D55: 9301 | E55: 11315 | F55: 13640 | G55: 23860 | H55: 33500 | I55: 35000 | J55: 32000 | K55: 31000 | L55: 28000 | M55: 27500
A56: FY2025 Revenue | B56: =SUM(B55:E55) -> 37379
A57: FY2026E Revenue | B57: =SUM(F55:I55) -> 106000
A58: FY2027E Revenue | B58: =SUM(J55:M55) -> 118500
A60: DRAM Revenue | B60: =B55*B10 -> 6358.3 | C60: =C55*C10 -> 6120.28 | D60: =D55*D10 -> 7068.76 | E60: =E55*E10 -> 9052 | F60: =F55*F10 -> 10775.6 | G60: =G55*G10 -> 18849.4 | H60: =H55*H10 -> 26800 | I60: =I55*I10 -> 28000 | ... M60: =M55*M10 -> 21450
A61: NAND Revenue | B61: =B55-B60 -> 2351.7 | C61: =C55-C60 -> 1932.72 | D61: =D55-D60 -> 2232.24 | E61: =E55-E60 -> 2263 | F61: =F55-F60 -> 2864.4 | G61: =G55-G60 -> 5010.6 | H61: =H55-H60 -> 6700 | I61: =I55-I60 -> 7000 | ... M61: =M55-M60 -> 6050
A62: HBM Revenue | B62: =B60*B12 -> 762.996 | C62: =C60*C12 -> 918.042 | D62: =D60*D12 -> 1272.3768 | E62: =E60*E12 -> 1991.44 | F62: =F60*F12 -> 3017.168 | G62: =G60*G12 -> 6031.808 | H62: =H60*H12 -> 9380 | I62: =I60*I12 -> 10640 | ... M62: =M60*M12 -> 9438
A63: Gross Profit | B63: =B55*B15 -> 3440.45 | C63: =C55*C15 -> 2963.504 | D63: =D55*D15 -> 3506.477 | E63: =E55*E15 -> 5057.805 | F63: =F55*F15 -> 7747.52 | G63: =G55*G15 -> 17895 | H63: =H55*H15 -> 27135 | I63: =I55*I15 -> 27300 | ... M63: =M55*M15 -> 17325
A64: R&D Expense | B64: =B55*B17 -> 1001.65 | C64: =C55*C17 -> 966.36 | D64: =D55*D17 -> 1023.11 | E64: =E55*E17 -> 1074.925 | F64: =F55*F17 -> 1159.4 | G64: =G55*G17 -> 1312.3 | H64: =H55*H17 -> 1507.5 | I64: =I55*I17 -> 1680 | ... M64: =M55*M17 -> 1705
A65: SG&A Expense | B65: =B55*B18 -> 348.4 | C65: =C55*C18 -> 338.226 | D65: =D55*D18 -> 353.438 | E65: =E55*E18 -> 362.08 | F65: =F55*F18 -> 381.92 | G65: =G55*G18 -> 477.2 | H65: =H55*H18 -> 603 | I65: =I55*I18 -> 700 | ... M65: =M55*M18 -> 825
A66: Operating Income | B66: =B63-B64-B65 -> 2090.4 | C66: =C63-C64-C65 -> 1658.918 | D66: =D63-D64-D65 -> 2129.929 | E66: =E63-E64-E65 -> 3620.8 | F66: =F63-F64-F65 -> 6206.2 | G66: =G63-G64-G65 -> 16105.5 | H66: =H63-H64-H65 -> 25024.5 | I66: =I63-I64-I65 -> 24920 | ... M66: =M63-M64-M65 -> 14795
A67: Net Income (approx) | B67: =B66*(1-B19) -> 1850.004 | C67: =C66*(1-C19) -> 1468.1424 | D67: =D66*(1-D19) -> 1884.9872 | E67: =E66*(1-E19) -> 3204.408 | F67: =F66*(1-F19) -> 5269.0638 | G67: =G66*(1-G19) -> 13673.569 | H67: =H66*(1-H19) -> 21245.801 | I67: =I66*(1-I19) -> 21157.08 | ... M67: =M66*(1-M19) -> 12560.955
A68: EPS (approx) | B68: =B67/B26 -> 1.6547442 | C68: =C67/C26 -> 1.3108415 | D68: =D67/D26 -> 1.6755441 | E68: =E67/E26 -> 2.833252 | F68: =F67/F26 -> 4.6301088 | G68: =G67/G26 -> 11.973353 | H68: =H67/H26 -> 18.555284 | I68: =I67/I26 -> 18.429512 | ... M68: =M67/M26 -> 11.36738
A69: FY2026E EPS | B69: =SUM(F68:I68) -> 53.588259
A70: FY2027E EPS | B70: =SUM(J68:M68) -> 52.427614
A72: Net CapEx ($B) | B72: =B22-B23 -> 2.8 | C72: =C22-C23 -> 3 | D72: =D22-D23 -> 3.2 | E72: =E22-E23 -> 3.5 | F72: =F22-F23 -> 4.2 | G72: =G22-G23 -> 4.7 | H72: =H22-H23 -> 6.7 | I72: =I22-I23 -> 8.2 | ... M72: =M22-M23 -> 10.2

Sheet Historical P&L
A1: MICRON TECHNOLOGY — HISTORICAL INCOME STATEMENT
A2: All figures in $M unless noted | Source: Micron 10-Q/10-K filings
B4: FQ1-25 Nov 2024 | C4: FQ2-25 Feb 2025 | D4: FQ3-25 May 2025 | E4: FQ4-25 Aug 2025 | F4: FQ1-26 Nov 2025 | G4: FQ2-26 Feb 2026 | H4: FY2025 | I4: FY2026 (H1)
B5: ACTUAL | C5: ACTUAL | D5: ACTUAL | E5: ACTUAL | F5: ACTUAL | G5: ACTUAL | H5: ACTUAL | I5: ACTUAL
A7: REVENUE
A8: Total Revenue | B8: =Assumptions!B55 -> 8710 | C8: =Assumptions!C55 -> 8053 | D8: =Assumptions!D55 -> 9301 | E8: =Assumptions!E55 -> 11315 | F8: =Assumptions!F55 -> 13640 | G8: =Assumptions!G55 -> 23860 | H8: =SUM(B8:E8) -> 37379 | I8: =SUM(F8:G8) -> 37500
A9: Revenue QoQ (%) | C9: =(C8-B8)/B8 -> -0.07543054 | D9: =(D8-C8)/C8 -> 0.1549733 | E9: =(E8-D8)/D8 -> 0.21653586 | F9: =(F8-E8)/E8 -> 0.20547945 | G9: =(G8-F8)/F8 -> 0.74926686
A10: DRAM Revenue | B10: =Assumptions!B60 -> 6358.3 | C10: =Assumptions!C60 -> 6120.28 | D10: =Assumptions!D60 -> 7068.76 | E10: =Assumptions!E60 -> 9052 | F10: =Assumptions!F60 -> 10775.6 | G10: =Assumptions!G60 -> 18849.4 | H10: =SUM(B10:E10) -> 28599.34 | I10: =SUM(F10:G10) -> 29625
A11: NAND Revenue | B11: =Assumptions!B61 -> 2351.7 | C11: =Assumptions!C61 -> 1932.72 | D11: =Assumptions!D61 -> 2232.24 | E11: =Assumptions!E61 -> 2263 | F11: =Assumptions!F61 -> 2864.4 | G11: =Assumptions!G61 -> 5010.6 | H11: =SUM(B11:E11) -> 8779.66 | I11: =SUM(F11:G11) -> 7875
A12: Other Revenue | B12: =B8-B10-B11 -> 0 | C12: =C8-C10-C11 -> 0 | D12: =D8-D10-D11 -> 0 | E12: =E8-E10-E11 -> 0 | F12: =F8-F10-F11 -> 0 | G12: =G8-G10-G11 -> 0 | H12: =SUM(B12:E12) -> 0 | I12: =SUM(F12:G12) -> 0
A13: DRAM % of Revenue | B13: =B10/B8 -> 0.73 | C13: =C10/C8 -> 0.76 | D13: =D10/D8 -> 0.76 | E13: =E10/E8 -> 0.8 | F13: =F10/F8 -> 0.79 | G13: =G10/G8 -> 0.79 | H13: =H10/H8 -> 0.76511785 | I13: =I10/I8 -> 0.79
A15: PROFITABILITY
A16: COGS | B16: =Assumptions!B55*(1-Assumptions!B15) -> 5269.55 | C16: =Assumptions!C55*(1-Assumptions!C15) -> 5089.496 | D16: =Assumptions!D55*(1-Assumptions!D15) -> 5794.523 | E16: =Assumptions!E55*(1-Assumptions!E15) -> 6257.195 | F16: =Assumptions!F55*(1-Assumptions!F15) -> 5892.48 | G16: =Assumptions!G55*(1-Assumptions!G15) -> 5965 | H16: =SUM(B16:E16) -> 22410.764 | I16: =SUM(F16:G16) -> 11857.48
A17: Gross Profit | B17: =B8-B16 -> 3440.45 | C17: =C8-C16 -> 2963.504 | D17: =D8-D16 -> 3506.477 | E17: =E8-E16 -> 5057.805 | F17: =F8-F16 -> 7747.52 | G17: =G8-G16 -> 17895 | H17: =H8-H16 -> 14968.236 | I17: =I8-I16 -> 25642.52
A18: Gross Margin (%) | B18: =B17/B8 -> 0.395 | C18: =C17/C8 -> 0.368 | D18: =D17/D8 -> 0.377 | E18: =E17/E8 -> 0.447 | F18: =F17/F8 -> 0.568 | G18: =G17/G8 -> 0.75 | H18: =H17/H8 -> 0.40044506 | I18: =I17/I8 -> 0.68380053
A20: Research & Development | B20: =Assumptions!B64 -> 1001.65 | C20: =Assumptions!C64 -> 966.36 | D20: =Assumptions!D64 -> 1023.11 | E20: =Assumptions!E64 -> 1074.925 | F20: =Assumptions!F64 -> 1159.4 | G20: =Assumptions!G64 -> 1312.3 | H20: =SUM(B20:E20) -> 4066.045 | I20: =SUM(F20:G20) -> 2471.7
A21: Selling, General & Admin | B21: =Assumptions!B65 -> 348.4 | C21: =Assumptions!C65 -> 338.226 | D21: =Assumptions!D65 -> 353.438 | E21: =Assumptions!E65 -> 362.08 | F21: =Assumptions!F65 -> 381.92 | G21: =Assumptions!G65 -> 477.2 | H21: =SUM(B21:E21) -> 1402.144 | I21: =SUM(F21:G21) -> 859.12
A22: Total Operating Expenses | B22: =B20+B21 -> 1350.05 | C22: =C20+C21 -> 1304.586 | D22: =D20+D21 -> 1376.548 | E22: =E20+E21 -> 1437.005 | F22: =F20+F21 -> 1541.32 | G22: =G20+G21 -> 1789.5 | H22: =H20+H21 -> 5468.189 | I22: =I20+I21 -> 3330.82
A24: Operating Income | B24: =B17-B22 -> 2090.4 | C24: =C17-C22 -> 1658.918 | D24: =D17-D22 -> 2129.929 | E24: =E17-E22 -> 3620.8 | F24: =F17-F22 -> 6206.2 | G24: =G17-G22 -> 16105.5 | H24: =H17-H22 -> 9500.047 | I24: =I17-I22 -> 22311.7
A25: Operating Margin (%) | B25: =B24/B8 -> 0.24 | C25: =C24/C8 -> 0.206 | D25: =D24/D8 -> 0.229 | E25: =E24/E8 -> 0.32 | F25: =F24/F8 -> 0.455 | G25: =G24/G8 -> 0.675 | H25: =H24/H8 -> 0.25415466 | I25: =I24/I8 -> 0.59497867
A27: Interest Expense, net | B27: -42 | C27: -4 | D27: 12 | E27: 22 | F27: 50 | G27: 80 | H27: =SUM(B27:E27) -> -12 | I27: =SUM(F27:G27) -> 130
A28: Other Income / (Expense) | B28: -68 | C28: -11 | D28: -68 | E28: -45 | F28: -20 | G28: -20 | H28: =SUM(B28:E28) -> -192 | I28: =SUM(F28:G28) -> -40
A29: Pre-Tax Income | B29: =B24+B27+B28 -> 1980.4 | C29: =C24+C27+C28 -> 1643.918 | D29: =D24+D27+D28 -> 2073.929 | E29: =E24+E27+E28 -> 3597.8 | F29: =F24+F27+F28 -> 6236.2 | G29: =G24+G27+G28 -> 16165.5 | H29: =H24+H27+H28 -> 9296.047 | I29: =I24+I27+I28 -> 22401.7
A30: Income Tax Provision | B30: =B29*0.151 -> 299.0404 | C30: =C29*0.151 -> 248.23162 | D30: =D29*0.151 -> 313.16328 | E30: =E29*0.151 -> 543.2678 | F30: =F29*0.151 -> 941.6662 | G30: =G29*0.151 -> 2440.9905 | H30: =H29*0.151 -> 1403.7031 | I30: =I29*0.151 -> 3382.6567
A32: NET INCOME (GAAP) | B32: =B29-B30 -> 1681.3596 | C32: =C29-C30 -> 1395.6864 | D32: =D29-D30 -> 1760.7657 | E32: =E29-E30 -> 3054.5322 | F32: =F29-F30 -> 5294.5338 | G32: =G29-G30 -> 13724.51 | H32: =H29-H30 -> 7892.3439 | I32: =I29-I30 -> 19019.043
A34: GAAP EPS (Diluted) | B34: =B32/(Assumptions!B26) -> 1.5038995 | C34: =C32/(Assumptions!C26) -> 1.2461486 | D34: =D32/(Assumptions!D26) -> 1.5651251 | E34: =E32/(Assumptions!E26) -> 2.7007358 | F34: =F32/(Assumptions!F26) -> 4.6524902 | G34: =G32/(Assumptions!G26) -> 12.017959 | H34: =H32/(Assumptions!B26) -> 7.0593416 | I34: =I32/((Assumptions!F26+Assumptions!G26)/2) -> 16.683371
A35: Non-GAAP EPS (Diluted) | B35: 1.79 | C35: 1.56 | D35: 1.91 | E35: 3.03 | F35: 4.78 | G35: 12.2 | H35: =SUM(B35:E35) -> 8.29 | I35: =SUM(F35:G35) -> 16.98
A37: MEMO ITEMS
A38: HBM Revenue (est. $M) | B38: =Assumptions!B62 -> 762.996 | C38: =Assumptions!C62 -> 918.042 | D38: =Assumptions!D62 -> 1272.3768 | E38: =Assumptions!E62 -> 1991.44 | F38: =Assumptions!F62 -> 3017.168 | G38: =Assumptions!G62 -> 6031.808 | H38: =SUM(B38:E38) -> 4944.8548 | I38: =SUM(F38:G38) -> 9048.976
A39: HBM as % of DRAM Revenue | B39: =B38/B10 -> 0.12 | C39: =C38/C10 -> 0.15 | D39: =D38/D10 -> 0.18 | E39: =E38/E10 -> 0.22 | F39: =F38/F10 -> 0.28 | G39: =G38/G10 -> 0.32 | H39: =H38/H10 -> 0.17290101 | I39: =I38/I10 -> 0.30545067
A40: D&A (est. $M) | B40: 1950 | C40: 2000 | D40: 2088 | E40: 2200 | F40: 2500 | G40: 2700 | H40: =SUM(B40:E40) -> 8238 | I40: =SUM(F40:G40) -> 5200
A41: EBITDA | B41: =B24+B40 -> 4040.4 | C41: =C24+C40 -> 3658.918 | D41: =D24+D40 -> 4217.929 | E41: =E24+E40 -> 5820.8 | F41: =F24+F40 -> 8706.2 | G41: =G24+G40 -> 18805.5 | H41: =H24+H40 -> 17738.047 | I41: =I24+I40 -> 27511.7
A43: REVENUE BY BUSINESS UNIT
A44: Cloud Memory BU (CMBU) | E44: 4543 | F44: 5269 | G44: 7749
A45: Mobile & Client BU (MCBU) | E45: 3760 | F45: 4264 | G45: 7711
A46: Core Data Center BU (CDBU) | E46: 1577 | F46: 2388 | G46: 5687
A47: Automotive & Embedded BU (AEBU) | E47: 1434 | F47: 1719 | G47: 2708
A49: BU GROSS MARGINS (%)
E50: FQ4-25 | F50: FQ1-26 | G50: FQ2-26
A51: CMBU | E51: 0.59 | F51: 0.66 | G51: 0.74
A52: MCBU | E52: 0.36 | F52: 0.54 | G52: 0.79
A53: CDBU | E53: 0.41 | F53: 0.51 | G53: 0.74
A54: AEBU | E54: 0.31 | F54: 0.45 | G54: 0.68
A55: Non-HBM margins > HBM margins

Sheet Projected P&L
A1: MICRON TECHNOLOGY — PROJECTED INCOME STATEMENT
A2: All figures in $M unless noted | Base case scenario
B4: FQ3-26E Mar-May | C4: FQ4-26E Jun-Aug | D4: FQ1-27E Sep-Nov | E4: FQ2-27E Dec-Feb | F4: FQ3-27E Mar-May | G4: FQ4-27E Jun-Aug | H4: FY2026E | I4: FY2027E
B5: ESTIMATE | C5: ESTIMATE | D5: ESTIMATE | E5: ESTIMATE | F5: ESTIMATE | G5: ESTIMATE
A7: REVENUE
A8: Total Revenue | B8: =Assumptions!H55 -> 33500 | C8: =Assumptions!I55 -> 35000 | D8: =Assumptions!J55 -> 32000 | E8: =Assumptions!K55 -> 31000 | F8: =Assumptions!L55 -> 28000 | G8: =Assumptions!M55 -> 27500 | H8: ='Historical P&L'!F8+'Historical P&L'!G8+B8+C8 -> 106000 | I8: =SUM(D8:G8) -> 118500
A9: Revenue QoQ (%) | B9: =(B8-'Historical P&L'!G8)/'Historical P&L'!G8 -> 0.40402347 | C9: =(C8-B8)/B8 -> 0.044776119 | D9: =(D8-C8)/C8 -> -0.085714286 | E9: =(E8-D8)/D8 -> -0.03125 | F9: =(F8-E8)/E8 -> -0.096774194 | G9: =(G8-F8)/F8 -> -0.017857143
A10: DRAM Revenue | B10: =Assumptions!H60 -> 26800 | C10: =Assumptions!I60 -> 28000 | D10: =Assumptions!J60 -> 25280 | E10: =Assumptions!K60 -> 24490 | F10: =Assumptions!L60 -> 21840 | G10: =Assumptions!M60 -> 21450 | H10: ='Historical P&L'!F10+'Historical P&L'!G10+B10+C10 -> 84425 | I10: =SUM(D10:G10) -> 93060
A11: NAND Revenue | B11: =B8-B10 -> 6700 | C11: =C8-C10 -> 7000 | D11: =D8-D10 -> 6720 | E11: =E8-E10 -> 6510 | F11: =F8-F10 -> 6160 | G11: =G8-G10 -> 6050 | H11: ='Historical P&L'!F11+'Historical P&L'!G11+B11+C11 -> 21575 | I11: =SUM(D11:G11) -> 25440
A12: HBM Revenue (memo, $M) | B12: =Assumptions!H62 -> 9380 | C12: =Assumptions!I62 -> 10640 | D12: =Assumptions!J62 -> 10112 | E12: =Assumptions!K62 -> 10285.8 | F12: =Assumptions!L62 -> 9391.2 | G12: =Assumptions!M62 -> 9438 | H12: ='Historical P&L'!F38+'Historical P&L'!G38+B12+C12 -> 29068.976 | I12: =SUM(D12:G12) -> 39227
A14: PROFITABILITY
A15: Gross Margin (%) | B15: =Assumptions!H15 -> 0.81 | C15: =Assumptions!I15 -> 0.78 | D15: =Assumptions!J15 -> 0.72 | E15: =Assumptions!K15 -> 0.68 | F15: =Assumptions!L15 -> 0.65 | G15: =Assumptions!M15 -> 0.63
A16: Gross Profit | B16: =B8*B15 -> 27135 | C16: =C8*C15 -> 27300 | D16: =D8*D15 -> 23040 | E16: =E8*E15 -> 21080 | F16: =F8*F15 -> 18200 | G16: =G8*G15 -> 17325 | H16: ='Historical P&L'!F17+'Historical P&L'!G17+B16+C16 -> 80077.52 | I16: =SUM(D16:G16) -> 79645
A17: COGS | B17: =B8-B16 -> 6365 | C17: =C8-C16 -> 7700 | D17: =D8-D16 -> 8960 | E17: =E8-E16 -> 9920 | F17: =F8-F16 -> 9800 | G17: =G8-G16 -> 10175
A19: Research & Development | B19: =B8*Assumptions!H17 -> 1507.5 | C19: =C8*Assumptions!I17 -> 1680 | D19: =D8*Assumptions!J17 -> 1760 | E19: =E8*Assumptions!K17 -> 1798 | F19: =F8*Assumptions!L17 -> 1680 | G19: =G8*Assumptions!M17 -> 1705 | H19: ='Historical P&L'!F20+'Historical P&L'!G20+B19+C19 -> 5659.2 | I19: =SUM(D19:G19) -> 6943
A20: Selling, General & Admin | B20: =B8*Assumptions!H18 -> 603 | C20: =C8*Assumptions!I18 -> 700 | D20: =D8*Assumptions!J18 -> 800 | E20: =E8*Assumptions!K18 -> 837 | F20: =F8*Assumptions!L18 -> 784 | G20: =G8*Assumptions!M18 -> 825 | H20: ='Historical P&L'!F21+'Historical P&L'!G21+B20+C20 -> 2162.12 | I20: =SUM(D20:G20) -> 3246
A21: Total Operating Expenses | B21: =B19+B20 -> 2110.5 | C21: =C19+C20 -> 2380 | D21: =D19+D20 -> 2560 | E21: =E19+E20 -> 2635 | F21: =F19+F20 -> 2464 | G21: =G19+G20 -> 2530 | H21: =H19+H20 -> 7821.32 | I21: =I19+I20 -> 10189
A23: Operating Income | B23: =B16-B21 -> 25024.5 | C23: =C16-C21 -> 24920 | D23: =D16-D21 -> 20480 | E23: =E16-E21 -> 18445 | F23: =F16-F21 -> 15736 | G23: =G16-G21 -> 14795 | H23: =H16-H21 -> 72256.2 | I23: =I16-I21 -> 69456
A24: Operating Margin (%) | B24: =B23/B8 -> 0.747 | C24: =C23/C8 -> 0.712 | D24: =D23/D8 -> 0.64 | E24: =E23/E8 -> 0.595 | F24: =F23/F8 -> 0.562 | G24: =G23/G8 -> 0.538 | H24: =H23/H8 -> 0.68166226 | I24: =I23/I8 -> 0.58612658
A26: Interest Expense, net | B26: -10 | C26: -10 | D26: -10 | E26: -10 | F26: -10 | G26: -10 | H26: ='Historical P&L'!F27+'Historical P&L'!G27+B26+C26 -> 110 | I26: =SUM(D26:G26) -> -40
A27: Other Income | B27: 25 | C27: 25 | D27: 25 | E27: 25 | F27: 25 | G27: 25 | H27: 25 | I27: 25
A28: Pre-Tax Income | B28: =B23+B26+B27 -> 25039.5 | C28: =C23+C26+C27 -> 24935 | D28: =D23+D26+D27 -> 20495 | E28: =E23+E26+E27 -> 18460 | F28: =F23+F26+F27 -> 15751 | G28: =G23+G26+G27 -> 14810 | H28: =H23+H26+H27 -> 72391.2 | I28: =I23+I26+I27 -> 69441
A29: Tax Provision (15.1%) | B29: =B28*0.151 -> 3780.9645 | C29: =C28*0.151 -> 3765.185 | D29: =D28*0.151 -> 3094.745 | E29: =E28*0.151 -> 2787.46 | F29: =F28*0.151 -> 2378.401 | G29: =G28*0.151 -> 2236.31 | H29: =H28*0.151 -> 10931.071 | I29: =I28*0.151 -> 10485.591
A31: NET INCOME | B31: =B28-B29 -> 21258.535 | C31: =C28-C29 -> 21169.815 | D31: =D28-D29 -> 17400.255 | E31: =E28-E29 -> 15672.54 | F31: =F28-F29 -> 13372.599 | G31: =G28-G29 -> 12573.69 | H31: =H28-H29 -> 61460.129 | I31: =I28-I29 -> 58955.409
A33: Non-GAAP EPS (Diluted) | B33: 19.15 | C33: =C31/Assumptions!I26*1.02 -> 18.809418 | D33: =D31/Assumptions!J26*1.02 -> 15.568649 | E33: =E31/Assumptions!K26*1.02 -> 14.146895 | F33: =F31/Assumptions!L26*1.02 -> 12.200403 | G33: =G31/Assumptions!M26*1.02 -> 11.606483 | H33: ='Historical P&L'!F35+'Historical P&L'!G35+B33+C33 -> 54.939418 | I33: =SUM(D33:G33) -> 53.52243
A35: FY Revenue YoY (%) | H35: =(H8-'Historical P&L'!H8)/'Historical P&L'!H8 -> 1.8358169 | I35: =(I8-H8)/H8 -> 0.11792453
A37: KEY FORECAST OBSERVATIONS
A38: • FQ3-26E single quarter revenue ($33.5B) exceeds entire FY2024 ($25.1B)
A39: • FY2026E EPS trajectory implies >4x FY2025 EPS of $8.29
A40: • Base case assumes orderly margin normalization from 81% peak to 63% floor over 6 quarters

Sheet Balance Sheet & CF
A1: MICRON TECHNOLOGY — BALANCE SHEET & CASH FLOW
A2: All figures in $M | Source: Micron 10-Q/10-K filings
B4: FQ2-25 Feb 2025 | C4: FQ4-25 Aug 2025 | D4: FQ1-26 Nov 2025 | E4: FQ2-26 Feb 2026 | F4: FQ3-26E May 2026 | G4: FQ4-26E Aug 2026
A6: ASSETS
A7: Cash & Cash Equivalents | B7: 7552 | C7: 9642 | D7: 12000 | E7: 9642 | F7: =E7+E20-E27+300-E29 -> 10442 | G7: =F7+F20-F27+300-F29 -> 12292
A8: Short-Term Investments | B8: 663 | C8: 665 | D8: 5500 | E8: 7058 | F8: 8000 | G8: 9000
A9: Total Cash & Investments | B9: =B7+B8 -> 8215 | C9: =C7+C8 -> 10307 | D9: =D7+D8 -> 17500 | E9: =E7+E8 -> 16700 | F9: =F7+F8 -> 18442 | G9: =G7+G8 -> 21292
A10: Inventory | B10: 9007 | C10: 8355 | D10: 8200 | E10: 8000 | F10: 8000 | G10: 8500
A11: PP&E, net | B11: 42528 | C11: 46590 | D11: 48000 | E11: 50000 | F11: 48000 | G11: 52000
A12: Total Assets | B12: 73053 | C12: 82798 | D12: 80000 | E12: 82798 | F12: 92000 | G12: 102000
A14: LIABILITIES & EQUITY
A15: Total Debt | B15: 14355 | C15: 14577 | D15: 11800 | E15: 10100 | F15: 9500 | G15: 9000
A16: Total Equity | B16: 48633 | C16: 54165 | D16: 50000 | E16: 54165 | F16: 65000 | G16: 78000
A18: KEY BALANCE SHEET RATIOS
A19: Net Debt / (Net Cash) | B19: =B15-B9 -> 6140 | C19: =C15-C9 -> 4270 | D19: =D15-D9 -> -5700 | E19: =E15-E9 -> -6600 | F19: =F15-F9 -> -8942 | G19: =G15-G9 -> -12292
A21: CASH FLOW SUMMARY
B22: FQ1-26 | C22: FQ2-26 | D22: FQ3-26E | E22: FQ4-26E | F22: FY2026E
A23: Operating Cash Flow | B23: 8410 | C23: 11900 | D23: 17000 | E23: 18000 | F23: =SUM(B23:E23) -> 55310
A24: Capital Expenditures | B24: -4500 | C24: -5000 | D24: -7000 | E24: -8500 | F24: =SUM(B24:E24) -> -25000
A25: Free Cash Flow | B25: =B23+B24 -> 3910 | C25: =C23+C24 -> 6900 | D25: =D23+D24 -> 10000 | E25: =E23+E24 -> 9500 | F25: =F23+F24 -> 30310
A26: FCF Margin (%) | B26: 0.287 | C26: 0.289 | D26: 0.299 | E26: 0.284
A28: CAPITAL RETURN
A29: Share Buybacks | B29: -300 | C29: -350 | D29: -400 | E29: -500 | F29: =SUM(B29:E29) -> -1550
A30: Dividends Paid | B30: -131 | C30: -171 | D30: -171 | E30: -171 | F30: =SUM(B30:E30) -> -644
A31: Debt Paydown | B31: -2770 | C31: -1600 | D31: -600 | E31: -500 | F31: =SUM(B31:E31) -> -5470
A33: KEY CASH FLOW METRICS
A34: CapEx Intensity (CapEx/Rev) | B34: =-B24/B23*1.5 -> 0.80261593 | C34: =-C24/C23*1.5 -> 0.6302521 | D34: =-D24/D23*1.5 -> 0.61764706 | E34: =-E24/E23*1.5 -> 0.70833333
A35: FY2026E Gross CapEx ($M) | B35: 25000

Sheet Supply Model
A1: MICRON TECHNOLOGY — FAB-LEVEL SUPPLY MODEL
A2: Maps physical wafer capacity → bit output → revenue potential
A4: Fab Location | B4: Product Type | C4: Current Node | D4: Wafer Starts (K/month) | E4: Target Node (CY2026) | F4: Target Node (CY2027) | G4: Bits/Wafer Improvement | H4: Notes / Risk
A5: Boise, Idaho (existing) | B5: DRAM | C5: 1-beta | D5: 40 | E5: 1-gamma | F5: 1-gamma | G5: +30% | H5: Primary U.S. DRAM site; 1-gamma ramp H1-2026
A6: Hiroshima, Japan | B6: DRAM (EUV) | C6: 1-gamma | D6: 55 | E6: 1-gamma | F6: 1-delta prep | G6: +30% (done) | H6: First EUV fab; 1-gamma volume production; fastest yield ramp in history per mgmt
A7: Taiwan (Taichung) | B7: DRAM | C7: 1-beta/1-gamma | D7: 60 | E7: 1-gamma | F7: 1-gamma | G7: +30% | H7: RISK: Taiwan Strait geopolitical; ~25% of DRAM bit output
A8: Taiwan (Tongluo, acquired) | B8: DRAM | C8: Under equip. | D8: 0 | E8: Equipment install | F8: 1-gamma qual | G8: N/A | H8: Acquired site; cleanroom construction CapEx; volume 2028+
A9: Singapore | B9: NAND + HBM pkg | C9: 232L/300L | D9: 35 | E9: 300L NAND | F9: 300L+ | G9: +20% | H9: Advanced HBM packaging facility; HBM supply contribution CY2027 per mgmt
A10: Manassas, Virginia | B10: DRAM (legacy) | C10: 1-alpha | D10: 15 | E10: 1-alpha | F10: 1-alpha | G10: N/A | H10: $275M CHIPS PMT; onshoring legacy DRAM for defense/auto
A11: Idaho Fab 1 (NEW) | B11: DRAM | C11: Construction | D11: 0 | E11: Tool install | F11: Wafer output H2-2027 | G11: N/A | H11: Under construction; part of $150B 20-yr Idaho investment; wafer out H2-2027
A12: New York (Clay) Fab 1 | B12: DRAM | C12: Planning | D12: 0 | E12: Construction start late 2026 | F12: Vertical 2027 | G12: N/A | H12: $3.4B CHIPS grant allocation (reduced from $4.6B); online ~2030
A13: India (Sanand, Gujarat) | B13: ATMP only | C13: N/A (packaging) | D13: 0 | E13: 14M units/wk ramp | F13: Full capacity | G13: N/A | H13: $2.75B ATMP facility; production started Feb 2026; HBM module packaging
A14: Malaysia | B14: ATMP | C14: N/A | D14: 0 | E14: Ongoing | F14: Ongoing | G14: N/A | H14: Assembly/test/packaging; supports all product lines
A17: NODE TRANSITION MIX (% of DRAM bit output)
A18: Node | B18: CQ1-26 | C18: CQ2-26 | D18: CQ3-26 | E18: CQ4-26 | F18: CQ1-27 | G18: CQ2-27 | H18: CQ3-27 | I18: CQ4-27
A19: 1-alpha (legacy) | B19: 0.1 | C19: 0.08 | D19: 0.05 | E19: 0.03 | F19: 0.02 | G19: 0.01 | H19: 0.01 | I19: 0
A20: 1-beta | B20: 0.5 | C20: 0.37 | D20: 0.25 | E20: 0.17 | F20: 0.13 | G20: 0.09 | H20: 0.06 | I20: 0.04
A21: 1-gamma (EUV) | B21: 0.4 | C21: 0.55 | D21: 0.7 | E21: 0.8 | F21: 0.85 | G21: 0.88 | H21: 0.9 | I21: 0.9
A22: 1-delta (EUV, next gen) | B22: 0 | C22: 0 | D22: 0 | E22: 0 | F22: 0 | G22: 0.02 | H22: 0.03 | I22: 0.06
A24: COST-PER-BIT IMPROVEMENT BY NODE
A25: Node Transition | B25: Cost/Bit Improvement | C25: Key Technology | D25: Risk Factor
A26: 1-alpha → 1-beta | B26: 15-18% | C26: DUV litho optimization | D26: Low — mature transition
A27: 1-beta → 1-gamma | B27: 18-22% | C27: First EUV layer introduction | D27: Medium — EUV yield ramp; FASTEST ramp in MU history
A28: 1-gamma → 1-delta | B28: 15-20% (est.) | C28: Multi-layer EUV; High-NA EUV potential | D28: High — EUV cost overrun risk; timeline uncertain
A30: HBM WAFER ALLOCATION & TRADE RATIO
A31: HBM Generation | B31: Stack Height | C31: Capacity/Stack | D31: Trade Ratio (vs DDR5) | E31: Per-Die Yield | F31: Stack Yield | G31: Volume Status
A32: HBM3E | B32: 8-High | C32: 24 GB | D32: 3.0x | E32: 95% | F32: 66% | G32: Full volume; majority of CY2025 shipments
A33: HBM3E 12-High | B33: 12-High | C33: 36 GB | D33: 4.5x | E33: 95% | F33: 54% | G33: Volume shipping; dominant in FQ2-26
A34: HBM4 12-High | B34: 12-High | C34: 36 GB | D34: 4.8x | E34: 92% | F34: 38% | G34: Volume shipments began CQ1-2026; >60% BW vs HBM3E
A35: HBM4 16-High | B35: 16-High | C35: 48 GB | D35: 6.0x | E35: 90% | F35: 19% | G35: Sampled; yield is key challenge
A36: HBM4E | B36: 12/16-High | C36: 48-64 GB | D36: 5.5x (est.) | E36: TBD | F36: TBD | G36: In development; volume ramp CY2027
A38: Stack Yield Formula: | B38: =(Per-Die _xludf.Yield) ^ (Stack Height) -> #NAME? | E38: e.g., 95%^8 = 66%, 95%^12 = 54%, 92%^12 = 38%
A40: INDUSTRY DRAM SUPPLY/DEMAND BALANCE
B41: CY2024 | C41: CY2025 | D41: CY2026E | E41: CY2027E
A42: Industry DRAM Bit Supply Growth | B42: 0.08 | C42: 0.12 | D42: 0.14 | E42: 0.18
A43: Industry DRAM Bit Demand Growth | B43: 0.15 | C43: 0.2 | D43: 0.25 | E43: 0.2
A44: Supply/Demand Spread (- = tight) | B44: =B42-B43 -> -0.07 | C44: =C42-C43 -> -0.08 | D44: =D42-D43 -> -0.11 | E44: =E42-E43 -> -0.02
A46: MICRON STRATEGIC SHIFTS (2026)
A47: Initiative | B47: Timeline | C47: Impact | D47: Source
A48: Crucial consumer exit | B48: By FQ2-26 (done) | C48: All consumer DRAM/SSD capacity redirected to AI data center | F48: Micron CBO Sadana, 12/4/25. etnews.
A49: Stacked GDDR development | B49: Equip H2-26; samples 2027 | C49: Industry-first 4-layer GDDR stack; perf between DDR5 and HBM | F49: etnews 3/30/26. Preemptive vs Samsung/SKH.
A50: HBM4 volume production | B50: CQ1-2026 (shipping) | C50: >60% BW vs HBM3E; designed for NVIDIA Vera Rubin | F50: FQ2-26 earnings 3/18/26.
A51: Singapore HBM packaging | B51: Contributing CY2027 | C51: Meaningful HBM supply addition from advanced packaging | F51: FQ2-26 earnings call.
A52: India ATMP production | B52: Operational Feb 2026 | C52: 14M units/wk at full ramp; HBM module packaging | F52: PM Modi inauguration 2/26. etnews.
A54: SEMIANALYSIS KEY FINDINGS (April 2026)
A55: Metric | B55: Value | C55: Context | D55: Source
A56: Cycle characterization | B56: Once-in-40-year shortage | C56: Comparable to 1993 Windows PC cycle; not even at peak yet | F56: SemiAnalysis 'Memory Mania'
A57: Memory % of hyperscaler capex | B57: 30% in CY2026 | C57: Up from 8% in CY2023-24; 4x increase in 3 years | F57: SemiAnalysis via Tom's Hardware 4/3/26
A58: DRAM price forecast CY2026 | B58: >2x (more than double) | C58: Another double-digit ASP increase expected in CY2027 | F58: SemiAnalysis estimate
A59: HBM wafer consumption ratio | B59: 3x vs commodity (rising to 4x) | C59: HBM4 widens gap further; HBM4E even more | F59: SemiAnalysis 'Memory Mania'
A60: NVIDIA Rubin Ultra HBM | B60: 1 TB per GPU | C60: Pushes per-GPU HBM capacity to unprecedented levels | F60: SemiAnalysis roadmap
A61: NVIDIA supply terms | B61: Preferential pricing below market | C61: NVIDIA secures HBM at below standard rates due to volume | F61: SemiAnalysis via Tom's Hardware
A62: Hyperscaler combined capex CY2026 | B62: $710B | C62: Top 8 cloud providers combined | F62: TrendForce
A63: DDR5 contract pricing | B63: $7 -> $19.50/unit | C63: ~179% increase; Samsung 32GB DDR5 module $149 -> $239 | F63: Industry data / SoftwareSeni
A64: DRAM inventory (channel) | B64: ~8 weeks | C64: vs 31 weeks at 2023 glut peak; below 10 wks = shortage | F64: Medium/market data Q4-25
A65: Supply relief timeline | B65: Not until 2028 | C65: Intel CEO: 'No relief until 2028'; fab ramps: SKH 2027, Samsung P5 2028, MU Idaho 2027 | F65: Multiple sources; SemiAnalysis
A66: SK Hynix 2026 output | B66: Entire output presold | C66: DRAM, NAND, HBM all sold out for 2026 | F66: SK Hynix earnings call; SemiAnalysis
A67: Micron 2026 output | B67: Sold out for 2026 | C67: Only satisfying 50-65% of demand from key customers | F67: Micron FQ2-26 earnings; SemiAnalysis
A69: HBM MARKET SHARE & CUSTOMER ALLOCATION
A70: Supplier | B70: HBM Share (Q2-25) | C70: Key Customer | D70: Allocation Detail
A71: SK Hynix | B71: 0.62 | C71: NVIDIA (primary) | D71: 2/3 of HBM supply for Vera Rubin; entire 2026 output presold
A72: Micron | B72: 0.21 | C72: NVIDIA + 5 others | D72: 100% CY2026 committed; 5-year SCA signed; targeting 25%
A73: Samsung | B73: 0.17 | C73: Google TPUs (primary) | D73: ~60% of HBM on Google TPUs; pursuing LTAs with MS/Google
A75: NEW CAPACITY TIMELINE (Supply Relief)
A76: Fab / Expansion | B76: Company | C76: Online Date | D76: Product | E76: Impact
A77: Cheongju expansion | B77: SK Hynix | C77: 2027 | D77: HBM + DRAM | E77: Incremental; not transformative
A78: West Lafayette, Indiana | B78: SK Hynix | C78: 2028 | D78: HBM packaging | E78: US ATMP capacity
A79: Pyeongtaek P5 | B79: Samsung | C79: 2028 | D79: DRAM + HBM | E79: Major new fab; meaningful supply
A80: Idaho Fab 1 | B80: Micron | C80: H2-2027 | D80: DRAM | E80: First wafer output; qual period follows
A81: Singapore pkg expansion | B81: Micron | C81: CY2027 | D81: HBM ATMP | E81: HBM packaging capacity addition
A82: New York Fab 1 (Clay) | B82: Micron | C82: ~2030 | D82: DRAM | E82: Delayed from 2028; long-dated
A84: TOTAL MEMORY MARKET TAM (TrendForce)
B85: CY2025 | C85: CY2026E | D85: CY2027E | E85: Growth
A86: Total Memory TAM ($B) | B86: 330 | C86: 552 | D86: 843
A87: YoY Growth | C87: =C86/B86-1 -> 0.67272727 | D87: =D86/C86-1 -> 0.52717391
A88: Micron Rev Share of TAM | B88: 0.113 | C88: 0.192 | D88: 0.157
A89: HBM as % of DRAM TAM | B89: 0.15 | C89: 0.25 | D89: 0.3

Sheet Bit Economics
A1: DRAM & NAND BIT-LEVEL ECONOMICS
A2: Bottom-up revenue decomposition: Bits Shipped x ASP/bit = Revenue | The physics-to-revenue bridge
A4: DRAM BIT ECONOMICS
B5: FQ1-25 (A) | C5: FQ2-25 (A) | D5: FQ3-25 (A) | E5: FQ4-25 (A) | F5: FQ1-26 (A) | G5: FQ2-26 (A) | H5: FQ3-26E | I5: FQ4-26E | J5: FQ1-27E | K5: FQ2-27E
A7: DRAM Wafer Starts (K/month) | B7: 165 | C7: 168 | D7: 170 | E7: 172 | F7: 175 | G7: 178 | H7: 180 | I7: 183 | J7: 185 | K7: 188
A8: Bits/Wafer Index (1-beta = 100) | B8: 100 | C8: 102 | D8: 106 | E8: 112 | F8: 120 | G8: 128 | H8: 135 | I8: 140 | J8: 143 | K8: 145
A9: DRAM Bit Output Growth QoQ (%) | C9: =(C7*C8)/(B7*B8)-1 -> 0.038545455 | D9: =(D7*D8)/(C7*C8)-1 -> 0.051587302 | E9: =(E7*E8)/(D7*D8)-1 -> 0.069034406 | F9: =(F7*F8)/(E7*E8)-1 -> 0.090116279 | G9: =(G7*G8)/(F7*F8)-1 -> 0.084952381 | H9: =(H7*H8)/(G7*G8)-1 -> 0.066537921 | I9: =(I7*I8)/(H7*H8)-1 -> 0.054320988 | J9: =(J7*J8)/(I7*I8)-1 -> 0.032591725 | K9: =(K7*K8)/(J7*J8)-1 -> 0.03042903
A10: HBM Wafer Allocation (K/month) | B10: 12 | C10: 14 | D10: 16 | E10: 20 | F10: 25 | G10: 32 | H10: 38 | I10: 42 | J10: 45 | K10: 48
A11: Effective Trade Ratio (HBM vs DDR5) | B11: 3 | C11: 3 | D11: 3.2 | E11: 3.5 | F11: 3.8 | G11: 4.2 | H11: 4.5 | I11: 4.5 | J11: 4.8 | K11: 4.8
A12: DDR5-Equivalent Wafers Lost to HBM | B12: =B10*B11 -> 36 | C12: =C10*C11 -> 42 | D12: =D10*D11 -> 51.2 | E12: =E10*E11 -> 70 | F12: =F10*F11 -> 95 | G12: =G10*G11 -> 134.4 | H12: =H10*H11 -> 171 | I12: =I10*I11 -> 189 | ... K12: =K10*K11 -> 230.4
A13: Net Commodity DRAM Wafers (K/mo) | B13: =B7-B12 -> 129 | C13: =C7-C12 -> 126 | D13: =D7-D12 -> 118.8 | E13: =E7-E12 -> 102 | F13: =F7-F12 -> 80 | G13: =G7-G12 -> 43.6 | H13: =H7-H12 -> 9 | I13: =I7-I12 -> -6 | ... K13: =K7-K12 -> -42.4
A15: DRAM ASP DECOMPOSITION
A16: Blended DRAM ASP ($/Gb, indexed) | B16: 1 | C16: 1.05 | D16: 1.15 | E16: 1.35 | F16: 1.7 | G16: 2.45 | H16: 3.1 | I16: 3.4 | J16: 3.5 | K16: 3.53
A17: ASP QoQ Change (%) | C17: =(C16-B16)/B16 -> 0.05 | D17: =(D16-C16)/C16 -> 0.095238095 | E17: =(E16-D16)/D16 -> 0.17391304 | F17: =(F16-E16)/E16 -> 0.25925926 | G17: =(G16-F16)/F16 -> 0.44117647 | H17: =(H16-G16)/G16 -> 0.26530612 | I17: =(I16-H16)/H16 -> 0.096774194 | J17: =(J16-I16)/I16 -> 0.029411765 | K17: =(K16-J16)/J16 -> 0.0085714286
A18: DRAM Cost/Gb Index (1-beta = 1.00) | B18: 1 | C18: 0.96 | D18: 0.91 | E18: 0.86 | F18: 0.8 | G18: 0.74 | H18: 0.7 | I18: 0.66 | J18: 0.63 | K18: 0.6
A19: ASP/Cost Spread (Margin Driver) | B19: =B16/B18 -> 1 | C19: =C16/C18 -> 1.09375 | D19: =D16/D18 -> 1.2637363 | E19: =E16/E18 -> 1.5697674 | F19: =F16/F18 -> 2.125 | G19: =G16/G18 -> 3.3108108 | H19: =H16/H18 -> 4.4285714 | I19: =I16/I18 -> 5.1515152 | ... K19: =K16/K18 -> 5.8833333
A21: DRAM REVENUE BRIDGE (Bottom-Up Check)
A22: Volume Effect (bit growth x prior ASP) | C22: =C9*B16 -> 0.038545455 | D22: =D9*C16 -> 0.054166667 | E22: =E9*D16 -> 0.079389567 | F22: =F9*E16 -> 0.12165698 | G22: =G9*F16 -> 0.14441905 | H22: =H9*G16 -> 0.16301791 | I22: =I9*H16 -> 0.16839506 | J22: =J9*I16 -> 0.11081187 | K22: =K9*J16 -> 0.10650161
A23: Price Effect (ASP change x prior volume) | C23: =C17*(1-C9) -> 0.048072727 | D23: =D17*(1-D9) -> 0.090325019 | E23: =E17*(1-E9) -> 0.16190706 | F23: =F17*(1-F9) -> 0.23589578 | G23: =G17*(1-G9) -> 0.40369748 | H23: =H17*(1-H9) -> 0.2476532 | I23: =I17*(1-I9) -> 0.091517324 | J23: =J17*(1-J9) -> 0.028453185 | K23: =K17*(1-K9) -> 0.0083106083
A24: Revenue Growth Attribution
A27: NAND BIT ECONOMICS (Condensed)
B28: FQ1-25 (A) | C28: FQ2-25 (A) | D28: FQ3-25 (A) | E28: FQ4-25 (A) | F28: FQ1-26 (A) | G28: FQ2-26 (A) | H28: FQ3-26E | I28: FQ4-26E | J28: FQ1-27E | K28: FQ2-27E
A29: NAND Wafer Starts (K/month) | B29: 35 | C29: 35 | D29: 35 | E29: 35 | F29: 36 | G29: 36 | H29: 37 | I29: 38 | J29: 38 | K29: 39
A30: NAND Layers (Current Gen) | B30: 232 | C30: 232 | D30: 232 | E30: 232 | F30: 232 | G30: 276 | H30: 300 | I30: 300 | J30: 300 | K30: 300
A31: NAND Bits/Wafer Index (232L = 100) | B31: 100 | C31: 100 | D31: 100 | E31: 102 | F31: 105 | G31: 115 | H31: 125 | I31: 128 | J31: 130 | K31: 132
A32: NAND Blended ASP Index | B32: 1 | C32: 1.03 | D32: 1.1 | E32: 1.2 | F32: 1.45 | G32: 2.3 | H32: 3 | I32: 3.25 | J32: 3.28 | K32: 3.3
A33: NAND ASP QoQ Change (%) | C33: =(C32-B32)/B32 -> 0.03 | D33: =(D32-C32)/C32 -> 0.067961165 | E33: =(E32-D32)/D32 -> 0.090909091 | F33: =(F32-E32)/E32 -> 0.20833333 | G33: =(G32-F32)/F32 -> 0.5862069 | H33: =(H32-G32)/G32 -> 0.30434783 | I33: =(I32-H32)/H32 -> 0.083333333 | J33: =(J32-I32)/I32 -> 0.0092307692 | K33: =(K32-J32)/J32 -> 0.006097561
A35: INDUSTRY BIT SUPPLY GROWTH VS MICRON
B36: CY2024 (A) | C36: CY2025 (A) | D36: CY2026E | E36: CY2027E
A37: Industry DRAM Bit Supply Growth | B37: 0.08 | C37: 0.12 | D37: 0.14 | E37: 0.18
A38: Micron DRAM Bit Supply Growth | B38: 0.06 | C38: 0.1 | D38: 0.12 | E38: 0.15
A39: Micron NAND Bit Supply Growth | B39: 0.05 | C39: 0.08 | D39: 0.12 | E39: 0.1
A41: KEY INSIGHT
A42: HBM wafer allocation acts as a supply governor on commo...
A44: DRAM YIELD CURVE MODEL BY NODE
A45: Quarter into Ramp | B45: Q1 | C45: Q2 | D45: Q3 | E45: Q4 | F45: Q5 | G45: Q6 | H45: Q7 | I45: Q8+
A46: 1-beta Yield (%) | B46: 0.7 | C46: 0.78 | D46: 0.85 | E46: 0.9 | F46: 0.93 | G46: 0.95 | H46: 0.96 | I46: 0.96
A47: 1-gamma Yield (%) — CURRENT RAMP | B47: 0.62 | C47: 0.72 | D47: 0.8 | E47: 0.86 | F47: 0.91 | G47: 0.93 | H47: 0.95 | I47: 0.95
A48: 1-delta Yield (%) — PROJECTED | B48: 0.55 | C48: 0.63 | D48: 0.72 | E48: 0.78 | F48: 0.83 | G48: 0.88 | H48: 0.91 | I48: 0.93
A49: Yield Ramp Impact on Cost/Bit
A50: At 62% yield, effective cost/die is ~61% higher than at...
A52: HBM STACK ECONOMICS — UNIT-LEVEL P&L
B53: HBM3E 8-High | C53: HBM3E 12-High | D53: HBM4 12-High | E53: HBM4 16-High | F53: HBM4E 12-High
A54: DRAM Dies per Stack | B54: 8 | C54: 12 | D54: 12 | E54: 16 | F54: 12
A55: Capacity per Stack (GB) | B55: 24 | C55: 36 | D55: 36 | E55: 48 | F55: 48
A56: Logic Die (base die) | B56: 1 | C56: 1 | D56: 1 | E56: 1 | F56: 1
A57: Total Dies per Stack | B57: 9 | C57: 13 | D57: 13 | E57: 17 | F57: 13
A58: Per-Die Yield (%) | B58: 0.95 | C58: 0.95 | D58: 0.92 | E58: 0.9 | F58: 0.93
A59: Stack Yield (%) | B59: =B58^B57 -> 0.63024941 | C59: =C58^C57 -> 0.51334208 | D59: =D58^D57 -> 0.33825308 | E59: =E58^E57 -> 0.16677182 | F59: =F58^F57 -> 0.38929456
A60: Dies Consumed per Good Stack | B60: =B57/B59 -> 14.280061 | C60: =C57/C59 -> 25.324244 | D60: =D57/D59 -> 38.432762 | E60: =E57/E59 -> 101.93569 | F60: =F57/F59 -> 33.393737
A61: Wafer Area per Die (mm²) | B61: 65 | C61: 65 | D61: 70 | E61: 70 | F61: 72
A62: Wafers per Stack (equiv.) | B62: =B60*B61/50000 -> 0.018564079 | C62: =C60*C61/50000 -> 0.032921517 | D62: =D60*D61/50000 -> 0.053805867 | E62: =E60*E61/50000 -> 0.14270996 | F62: =F60*F61/50000 -> 0.048086981
A63: DRAM Wafer Cost ($) | B63: 3500 | C63: 3500 | D63: 4200 | E63: 4200 | F63: 4500
A64: Base Die Wafer Cost ($) | B64: 2500 | C64: 2500 | D64: 3000 | E64: 3000 | F64: 3200
A65: TSV + Stacking Cost ($) | B65: 200 | C65: 350 | D65: 400 | E65: 600 | F65: 450
A66: Test & Packaging ($) | B66: 150 | C66: 200 | D66: 250 | E66: 350 | F66: 280
A67: Total Stack COGS ($) | B67: =B62*B63 + B64*0.15 + B65 + B66 -> 789.97428 | C67: =C62*C63 + C64*0.15 + C65 + C66 -> 1040.2253 | D67: =D62*D63 + D64*0.15 + D65 + D66 -> 1325.9846 | E67: =E62*E63 + E64*0.15 + E65 + E66 -> 1999.3818 | F67: =F62*F63 + F64*0.15 + F65 + F66 -> 1426.3914
A68: ASP per Stack ($) | B68: 720 | C68: 1260 | D68: 1800 | E68: 2800 | F68: 2400
A69: Gross Margin per Stack (%) | B69: =(B68-B67)/B68 -> -0.097186496 | C69: =(C68-C67)/C68 -> 0.17442436 | D69: =(D68-D67)/D68 -> 0.26334187 | E69: =(E68-E67)/E68 -> 0.28593505 | F69: =(F68-F67)/F68 -> 0.40567024
A70: ASP per GB ($) | B70: =B68/B56 -> 720 | C70: =C68/C56 -> 1260 | D70: =D68/D56 -> 1800 | E70: =E68/E56 -> 2800 | F70: =F68/F56 -> 2400
A72: REVENUE PER WAFER START — KEY CAPITAL EFFICIENCY METRIC
A73: Wafer Type | B73: Cost/Wafer | C73: Rev/Wafer (Current) | D73: Rev/Wafer (Peak) | E73: Gross Profit /Wafer | F73: Capital Efficiency Rating
A74: Commodity DDR5 (1-gamma) | B74: 3500 | C74: 8500 | D74: 12000 | E74: =C74-B74 -> 5000 | F74: GOOD
A75: HBM3E 12-High | B75: 3500 | C75: 35000 | D75: 42000 | E75: =C75-B75 -> 31500 | F75: EXCELLENT
A76: HBM4 12-High | B76: 4200 | C76: 45000 | D76: 55000 | E76: =C76-B76 -> 40800 | F76: EXCEPTIONAL
A77: NAND 232L | B77: 2800 | C77: 5500 | D77: 7000 | E77: =C77-B77 -> 2700 | F77: MODERATE
A78: NAND 300L | B78: 3200 | C78: 7500 | D78: 9500 | E78: =C78-B78 -> 4300 | F78: GOOD
A80: KEY INSIGHT: HBM4 generates ~10x revenue per wafer star...

Sheet HBM Contracts
A1: HBM CONTRACT & COMMITTED REVENUE FLOOR
A2: Quantifies the structural floor under Micron's revenue from contracted HBM
A4: HBM TOTAL ADDRESSABLE MARKET ($B)
B5: CY2024 | C5: CY2025E | D5: CY2026E | E5: CY2027E | F5: CY2028E
A6: Industry HBM TAM ($B) | B6: 16 | C6: 35 | D6: 55 | E6: 77 | F6: 100
A7: Micron HBM Market Share (%) | B7: 0.15 | C7: 0.21 | D7: 0.25 | E7: 0.26 | F7: 0.27
A8: Micron HBM Revenue ($B) | B8: =B6*B7 -> 2.4 | C8: =C6*C7 -> 7.35 | D8: =D6*D7 -> 13.75 | E8: =E6*E7 -> 20.02 | F8: =F6*F7 -> 27
A10: HBM CUSTOMER BASE (6 customers per mgmt)
A11: Customer | B11: Platform | C11: HBM Gen Required | D11: Est. % of MU HBM Rev | E11: Contract Type | F11: Risk Level
A12: NVIDIA | B12: Blackwell → Vera Rubin | C12: HBM3E → HBM4 | D12: 45-50% | E12: Multi-year SCA | F12: Low
A13: AMD | B13: MI350/MI400 AI accelerators | C13: HBM3E → HBM4 | D13: 15-20% | E13: Volume agreement | F13: Low-Med
A14: Google (TPU) | B14: TPU v6/v7 custom silicon | C14: HBM3E/HBM4 | D14: 10-15% | E14: Volume agreement | F14: Medium
A15: Amazon (Trainium) | B15: Trainium 3+ custom chip | C15: HBM3E/HBM4 | D15: 8-12% | E15: Volume agreement | F15: Medium
A16: Microsoft (Maia) | B16: Maia AI accelerator | C16: HBM4 | D16: 5-8% | E16: Volume agreement | F16: Medium
A17: Meta (MTIA) | B17: MTIA custom silicon | C17: HBM3E/HBM4 | D17: 5-8% | E17: Volume agreement | F17: Medium
A19: KEY MANAGEMENT DISCLOSURES ON HBM CONTRACTS
A20: CY2026 HBM 100% committed
A21: First 5-year SCA signed
A22: 50-65% of customer demand satisfied
A23: HBM TAM $100B by CY2028
A24: Singapore HBM pkg CY2027
A25: India ATMP operational Feb 2026
A26: HBM4 volume CQ1-2026
A28: INDUSTRY-WIDE LONG-TERM SUPPLY AGREEMENTS (April 2026)
A29: Buyer | B29: Supplier | C29: Products | D29: Duration | E29: Terms | F29: Status
A30: Microsoft | B30: SK Hynix | C30: DDR5 + HBM | D30: 3 years | E30: Tens of trillions KRW | F30: Final-stage negotiations
A31: Google | B31: SK Hynix | C31: HBM + commodity DRAM | D31: Multi-year | E31: Not disclosed | F31: In discussions
A32: Microsoft | B32: Samsung | C32: Memory (DRAM+HBM) | D32: 3-5 years | E32: Large advance payments | F32: Negotiating
A33: Google | B33: Samsung | C33: Memory (DRAM+HBM) | D33: 3-5 years | E33: Large advance payments | F33: Negotiating
A34: Multiple | B34: Micron | D34: 5 years (first) | E34: Price+volume locked | F34: SIGNED
A35: PROB-WEIGHTED REVENUE FLOOR | E35: 80.5
A36: LONG-TERM SCA KEY TERMS (per EBN/etnews reporting)
A37: Term | B37: Structure | C37: Source
A38: Price mechanism | B38: Linked to spot market rates with band ranges | E38: EBN: prices adjust if market moves beyond specified ranges. Not fixed-price. | G38: FQ2-26
A39: Upfront payment | B39: 10-30% of total contract value | E39: etnews 4/5/26: provisions for upfront payment of 10-30% of TCV. | G39: 7.5
A40: Volume commitment | B40: Fixed quantities; forfeiture if not purchased | E40: EBN: prepayments forfeited or credited if buyer fails to purchase committed volumes. | G40: =G39*Assumptions!G11 -> 46.5
A41: Price floor | B41: Under discussion | E41: etnews: discussions centered on price floor to hedge against significant DRAM ASP declines. | G41: =Assumptions!G11 -> 6.2
A42: Key difference vs 2019 | B42: Binding with enforcement | E42: EBN: 2019 contracts lacked enforcement; customers could cancel. New LTAs have prepayment forfeiture.
A44: HYPERSCALER PROCUREMENT BEHAVIOR (SemiAnalysis/SoftwareSeni)
A45: Company | B45: Behavior | C45: Source
A46: Google | B46: Fired procurement executive for failing to sign LTAs ahead of shortage | E46: SoftwareSeni compilation
A47: Microsoft | B47: Executives 'stormed out' of SK Hynix meetings over unmet terms | E47: SoftwareSeni
A48: Meta/Google | B48: Created roles: 'Memory Silicon Global Sourcing Manager' | E48: SoftwareSeni
A49: All hyperscalers | B49: Station dedicated procurement staff in South Korea | E49: SoftwareSeni
A50: NVIDIA | B50: Secures preferential HBM pricing below standard market rates | E50: SemiAnalysis via Tom's Hardware 4/3/26
A51: Top 8 CSPs | B51: Combined CY2026 capex: $710B (TrendForce) | E51: TrendForce projection
A53: NVIDIA VERA RUBIN HBM4 ALLOCATION (TrendForce 3/9/26)
A54: Platform | B54: Supplier | C54: Share | D54: HBM Gen | E54: Status | F54: Source
A55: Vera Rubin (flagship) | B55: SK Hynix | C55: ~70% | D55: HBM4 | E55: Primary supplier | F55: TrendForce 3/9/26
A56: Vera Rubin (flagship) | B56: Samsung | C56: ~30% | D56: HBM4 | E56: Secondary supplier | F56: TrendForce 3/9/26
A57: Vera Rubin (flagship) | B57: Micron | C57: 0% | D57: HBM4 | E57: NOT SELECTED for flagship | F57: TrendForce 3/9/26; WCCFTech
A58: Rubin CPX (inference) | B58: Micron | C58: Significant | D58: HBM4 | E58: Primary for inference variant | F58: Digitimes 1/7/26
A59: Blackwell (current) | B59: All 3 suppliers | C59: Split | D59: HBM3E | E59: All qualified and shipping | F59: Micron FQ2-26 earnings
A60: Rubin Ultra (future) | B60: TBD | C60: TBD | D60: HBM4E | E60: 1 TB per GPU; volume 2027+ | F60: SemiAnalysis roadmap
A62: CONTRACT STRUCTURE ANALYSIS (TrendForce/Analyst Research)
A63: Contract Type | B63: Duration | C63: Pricing | D63: Volume | E63: Enforcement | F63: Who Uses
A64: 5-Year SCA (Micron) | B64: 5 years | C64: Confidential; likely fixed w/ escalation | D64: Specific volume commitments | E64: Binding; 'robust provisions' | F64: Micron (1 signed, more in pipeline)
A65: Multi-Year LTA + Prepayment | B65: 3-5 years | C65: Spot-linked with band ranges | D65: Fixed quantities | E65: Prepayment forfeiture if volumes not met | F65: Samsung-MSFT ($10B+ prepay), Samsung-Google
A66: Post-Settlement (Short-Term) | B66: Quarterly/Monthly | C66: Retroactive to market rate at settlement | D66: Flexible | E66: Final payment adjusted to spot at contract end | F66: Samsung/SKH/MU for NA big-tech conventional DRAM
A67: Annual LTA (Traditional) | B67: 1 year | C67: Fixed quarterly negotiation | D67: Quarterly renegotiation | E67: Soft commitment; historically cancellable | F67: Legacy approach; being replaced
A68: HBM Volume/Price Lock | B68: Annual (CY basis) | C68: Price locked for calendar year | D68: 100% of annual output committed | E68: Non-cancellable per Micron mgmt | F68: All 3 suppliers for HBM; MU 100% CY2026 locked
A70: ESTIMATED REVENUE LOCK-IN (% of Forward Revenue)
A71: Revenue Category | B71: % of Total Rev | C71: Contract Status | D71: Confidence
A72: HBM (all gens) | B72: ~30% of DRAM rev | C72: 100% contracted CY2026 | D72: 0.95
A73: Enterprise DRAM (server DDR5) | B73: ~35% of DRAM rev | C73: LTA/post-settlement; mostly committed | D73: 0.8
A74: Enterprise NAND (SSD) | B74: ~70% of NAND rev | C74: Quarterly LTA; strong demand pull | D74: 0.75
A75: Mobile LPDDR5X | B75: ~25% of DRAM rev | C75: OEM contracts; semi-committed | D75: 0.65
A76: Spot/channel (post-Crucial exit) | B76: <5% of total rev | C76: Spot-exposed; minimal post-exit | D76: 0.5
A77: TOTAL ESTIMATED LOCKED-IN REVENUE | D77: 0.78
A79: 5-YEAR SCA DETAILS (FQ2-26 Earnings Call 3/18/26)
A80: Detail | B80: Value | C80: Source / Context
A81: Customer | B81: Undisclosed | C81: 'Large customer' per Mehrotra. Strongly suspected NVIDIA.
A82: Duration | B82: 5 years | C82: Unprecedented for memory; standard LTA = 1 year.
A83: Scope | B83: Broad product portfolio | C83: Not limited to HBM; covers DRAM/NAND.
A84: Pricing terms | B84: Confidential | C84: 'Robust provisions' per Mehrotra. Not disclosed.
A85: Volume terms | B85: Specific commitments | C85: 'Specific commitments over a multiyear time horizon.'
A86: Cycle protection | B86: Spans up and down cycles | C86: 'Go across periods when industry is very tight versus other parts.'
A87: R&D integration | B87: Roadmap planning included | C87: Closer collaboration on future product development.
A88: Pipeline | B88: Multiple others in discussion | C88: 'In discussions with multiple other customers across markets.'
A89: Key analyst Qs | B89: Barclays: downside risk terms? | C89: Mehrotra declined specifics. Cantor: does it extend beyond hyperscalers?
A91: POST-SETTLEMENT PRICING MODEL (TrendForce 2/6/26)
A92: Mechanism | B92: Price agreed at delivery; final payment adjusted to market rate at contract end
A93: Effect on Micron | B93: Captures 100% of price upside on conventional DRAM; no cap on seller benefit in rising market
A94: Spot vs Contract (Mar 2026) | B94: TrendForce 3/4/26: DRAM spot prices currently ABOVE contract prices — indicates genuine physical shortage
A96: OPENAI/STARGATE DRAM DEAL (Letter of Intent, Oct 2025)
A97: Parties | B97: Samsung + SK Hynix (Micron NOT included)
A98: Volume | B98: 900,000 wafers/month (~40% of global DRAM output)
A99: Status | B99: Letter of intent, not binding contract
A100: Micron implication | B100: Excluded from Stargate wafer deal. Reinforces risk of customer concentration at Samsung/SKH.

Sheet Debt Schedule
A1: MICRON TECHNOLOGY — DEBT MATURITY SCHEDULE
A2: Tracks individual debt tranches, maturities, and deleveraging trajectory
A4: OUTSTANDING DEBT TRANCHES (as of FQ2-26)
A5: Debt Instrument | B5: Original Amt ($M) | C5: Outstanding ($M) | D5: Coupon (%) | E5: Maturity | F5: Next Call Date | G5: YTM (est.) | H5: Status
A6: 2025 Senior Notes (4.185%) | B6: 1000 | C6: 0 | D6: 0.04185 | E6: Feb 2025 | F6: N/A | G6: N/A | H6: REPAID
A7: 2026 Senior Notes (4.640%) | B7: 1500 | C7: 750 | D7: 0.0464 | E7: Feb 2026 | F7: At maturity | G7: 0.046 | H7: Partial paydown
A8: 2027 Senior Notes (5.327%) | B8: 1750 | C8: 1750 | D8: 0.05327 | E8: Jan 2027 | F8: Jul 2026 | G8: 0.053 | H8: Outstanding
A9: 2028 Senior Notes (4.500%) | B9: 1000 | C9: 1000 | D9: 0.045 | E9: Sep 2028 | F9: Mar 2028 | G9: 0.045 | H9: Outstanding
A10: 2029 Senior Notes (6.750%) | B10: 2000 | C10: 800 | D10: 0.0675 | E10: Nov 2029 | F10: Aug 2029 | G10: 0.065 | H10: Redeemed $1.2B in FQ2-26
A11: 2030 Senior Notes (5.375%) | B11: 1500 | C11: 1100 | D11: 0.05375 | E11: Apr 2030 | F11: Jan 2030 | G11: 0.054 | H11: Partial redemption FQ2-26
A12: 2031 Senior Notes (4.750%) | B12: 1250 | C12: 1250 | D12: 0.0475 | E12: Feb 2031 | F12: Nov 2030 | G12: 0.048 | H12: Outstanding
A13: 2032 Senior Notes (5.875%) | B13: 1500 | C13: 1500 | D13: 0.05875 | E13: Sep 2032 | F13: Jun 2032 | G13: 0.059 | H13: Outstanding
A14: 2033 Senior Notes (5.300%) | B14: 1250 | C14: 1250 | D14: 0.053 | E14: Jan 2033 | F14: Oct 2032 | G14: 0.053 | H14: Outstanding
A15: Other (revolver, misc.) | B15: 700 | C15: 700 | D15: 0.055 | E15: Various | F15: Various | G15: 0.055 | H15: $3.5B revolver undrawn
A16: TOTAL OUTSTANDING DEBT | C16: =SUM(C6:C15) -> 10100
A17: Weighted Avg. Coupon (%) | C17: =SUMPRODUCT(C6:C15,D6:D15)/SUM(C6:C15) -> 0.053306683
A18: Weighted Avg. Maturity (Years) | C18: 4.8
A20: MATURITY WALL ($M coming due)
B21: FY2026 (Remaining) | C21: FY2027 | D21: FY2028 | E21: FY2029 | F21: FY2030 | G21: FY2031 | H21: FY2032+
A22: Maturities Due | B22: 750 | C22: 1750 | D22: 1000 | E22: 800 | F22: 1100 | G22: 1250 | H22: 3450
A23: Projected Paydowns (from FCF) | B23: -750 | C23: -1750 | D23: -1000 | E23: -800 | F23: -1100 | G23: -1250 | H23: -3450
A24: Remaining Debt Outstanding | B24: =C16+B22+B23 -> 10100 | C24: =B24+C22+C23 -> 10100 | D24: =C24+D22+D23 -> 10100 | E24: =D24+E22+E23 -> 10100 | F24: =E24+F22+F23 -> 10100 | G24: =F24+G22+G23 -> 10100 | H24: =G24+H22+H23 -> 10100
A26: NET DEBT / (NET CASH) TRAJECTORY
B27: FQ2-26 (Actual) | C27: FQ4-26E | D27: FQ4-27E | E27: FQ4-28E
A28: Total Debt | B28: 10100 | C28: 9000 | D28: 5000 | E28: 2000
A29: Cash & Investments | B29: 16700 | C29: 25000 | D29: 40000 | E29: 50000
A30: NET DEBT / (NET CASH) | B30: =B28-B29 -> -6600 | C30: =C28-C29 -> -16000 | D30: =D28-D29 -> -35000 | E30: =E28-E29 -> -48000
A31: Net Debt / LTM EBITDA | B31: -0.15 | C31: -0.3 | D31: -0.8 | E31: -1.2
A33: NOTE: Micron retired $4.37B of debt in H1-FY2026. At $35B+ FCF run-rate, the entire debt stack can be retired by FY2028.
A35: QUARTERLY INTEREST EXPENSE BUILD ($M)
A36: Debt Tranche | B36: Coupon | C36: Outstanding ($M) | D36: FQ3-26E | E36: FQ4-26E | F36: FQ1-27E | G36: FQ2-27E | H36: FQ3-27E | I36: FQ4-27E
A37: 2026 Notes (4.64%) | B37: 0.0464 | C37: 750 | D37: 750 | E37: 0 | F37: 0 | G37: 0 | H37: 0 | I37: 0
A38: 2027 Notes (5.327%) | B38: 0.05327 | C38: 1750 | D38: 1750 | E38: 1750 | F38: 0 | G38: 0 | H38: 0 | I38: 0
A39: 2028 Notes (4.50%) | B39: 0.045 | C39: 1000 | D39: 1000 | E39: 1000 | F39: 1000 | G39: 1000 | H39: 1000 | I39: 1000
A40: 2029 Notes (6.75%) | B40: 0.0675 | C40: 800 | D40: 800 | E40: 800 | F40: 800 | G40: 800 | H40: 800 | I40: 800
A41: 2030 Notes (5.375%) | B41: 0.05375 | C41: 1100 | D41: 1100 | E41: 1100 | F41: 1100 | G41: 1100 | H41: 1100 | I41: 1100
A42: 2031 Notes (4.75%) | B42: 0.0475 | C42: 1250 | D42: 1250 | E42: 1250 | F42: 1250 | G42: 1250 | H42: 1250 | I42: 1250
A43: 2032 Notes (5.875%) | B43: 0.05875 | C43: 1500 | D43: 1500 | E43: 1500 | F43: 1500 | G43: 1500 | H43: 1500 | I43: 1500
A44: 2033 Notes (5.30%) | B44: 0.053 | C44: 1250 | D44: 1250 | E44: 1250 | F44: 1250 | G44: 1250 | H44: 1250 | I44: 1250
A45: Other / Revolver | B45: 0.055 | C45: 700 | D45: 700 | E45: 500 | F45: 400 | G45: 300 | H45: 200 | I45: 100
A47: INTEREST EXPENSE BY TRANCHE ($M/quarter)
A48: 2026 Notes (4.64%) | D48: =D37*B37/4 -> 8.7 | E48: =E37*B37/4 -> 0 | F48: =F37*B37/4 -> 0 | G48: =G37*B37/4 -> 0 | H48: =H37*B37/4 -> 0 | I48: =I37*B37/4 -> 0
A49: 2027 Notes (5.327%) | D49: =D38*B38/4 -> 23.305625 | E49: =E38*B38/4 -> 23.305625 | F49: =F38*B38/4 -> 0 | G49: =G38*B38/4 -> 0 | H49: =H38*B38/4 -> 0 | I49: =I38*B38/4 -> 0
A50: 2028 Notes (4.50%) | D50: =D39*B39/4 -> 11.25 | E50: =E39*B39/4 -> 11.25 | F50: =F39*B39/4 -> 11.25 | G50: =G39*B39/4 -> 11.25 | H50: =H39*B39/4 -> 11.25 | I50: =I39*B39/4 -> 11.25
A51: 2029 Notes (6.75%) | D51: =D40*B40/4 -> 13.5 | E51: =E40*B40/4 -> 13.5 | F51: =F40*B40/4 -> 13.5 | G51: =G40*B40/4 -> 13.5 | H51: =H40*B40/4 -> 13.5 | I51: =I40*B40/4 -> 13.5
A52: 2030 Notes (5.375%) | D52: =D41*B41/4 -> 14.78125 | E52: =E41*B41/4 -> 14.78125 | F52: =F41*B41/4 -> 14.78125 | G52: =G41*B41/4 -> 14.78125 | H52: =H41*B41/4 -> 14.78125 | I52: =I41*B41/4 -> 14.78125
A53: 2031 Notes (4.75%) | D53: =D42*B42/4 -> 14.84375 | E53: =E42*B42/4 -> 14.84375 | F53: =F42*B42/4 -> 14.84375 | G53: =G42*B42/4 -> 14.84375 | H53: =H42*B42/4 -> 14.84375 | I53: =I42*B42/4 -> 14.84375
A54: 2032 Notes (5.875%) | D54: =D43*B43/4 -> 22.03125 | E54: =E43*B43/4 -> 22.03125 | F54: =F43*B43/4 -> 22.03125 | G54: =G43*B43/4 -> 22.03125 | H54: =H43*B43/4 -> 22.03125 | I54: =I43*B43/4 -> 22.03125
A55: 2033 Notes (5.30%) | D55: =D44*B44/4 -> 16.5625 | E55: =E44*B44/4 -> 16.5625 | F55: =F44*B44/4 -> 16.5625 | G55: =G44*B44/4 -> 16.5625 | H55: =H44*B44/4 -> 16.5625 | I55: =I44*B44/4 -> 16.5625
A56: Other / Revolver | D56: =D45*B45/4 -> 9.625 | E56: =E45*B45/4 -> 6.875 | F56: =F45*B45/4 -> 5.5 | G56: =G45*B45/4 -> 4.125 | H56: =H45*B45/4 -> 2.75 | I56: =I45*B45/4 -> 1.375
A57: TOTAL QUARTERLY INTEREST EXPENSE | D57: =SUM(D48:D56) -> 134.59938 | E57: =SUM(E48:E56) -> 123.14937 | F57: =SUM(F48:F56) -> 98.46875 | G57: =SUM(G48:G56) -> 97.09375 | H57: =SUM(H48:H56) -> 95.71875 | I57: =SUM(I48:I56) -> 94.34375
A59: INTEREST COVERAGE & CREDIT METRICS
A60: Quarterly EBITDA ($M, est.) | D60: 30000 | E60: 30000 | F60: 22000 | G60: 20000 | H60: 19000 | I60: 18000
A61: Interest Coverage (EBITDA/Interest) | D61: =D60/ABS(D57) -> 222.88365 | E61: =E60/ABS(E57) -> 243.6066 | F61: =F60/ABS(F57) -> 223.42114 | G61: =G60/ABS(G57) -> 205.98648 | H61: =H60/ABS(H57) -> 198.4982 | I61: =I60/ABS(I57) -> 190.79165
A62: Fixed Charge Coverage | D62: =D60/(ABS(D57)+500) -> 47.27392 | E62: =E60/(ABS(E57)+500) -> 48.14255 | F62: =F60/(ABS(F57)+500) -> 36.760482 | G62: =G60/(ABS(G57)+500) -> 33.495578 | H62: =H60/(ABS(H57)+500) -> 31.894245 | I62: =I60/(ABS(I57)+500) -> 30.285504
A64: REFINANCING RISK ASSESSMENT
A65: Risk Factor | B65: Exposure | C65: Assessment
A66: Near-term maturities (12 months) | B66: $750M (2026 notes) | C66: LOW — Easily covered by single quarter FCF ($6.9B+ FQ2-26)
A67: Medium-term maturities (12-36 mo) | B67: $2,750M (2027 + 2028 notes) | C67: LOW — <1 quarter of FCF; no refinancing needed
A68: Credit rating trajectory | B68: Investment Grade (BBB+ range) | C68: POSITIVE — Rapid deleveraging; net cash ...
A69: Covenant compliance | B69: No financial maintenance covenants | C69: N/A — Senior unsecured notes; no covenant risk
A70: Refinancing spread risk | B70: Current spread ~150bps over UST | C70: LOW — Credit improvement should tighten spreads
A71: Foreign currency debt exposure | B71: 100% USD-denominated | C71: NONE — No FX translation risk on debt

Sheet Working Capital
A1: WORKING CAPITAL & INVENTORY SCHEDULE
A2: DIO is the leading indicator of memory cycle position | Source: Micron 10-Q/10-K
B4: FQ2-25 (A) | C4: FQ4-25 (A) | D4: FQ1-26 (A) | E4: FQ2-26 (A) | F4: FQ3-26E | G4: FQ4-26E | H4: FQ1-27E
A6: INVENTORY
A7: Raw Materials ($M) | B7: 1200 | C7: 1100 | D7: 1000 | E7: 900 | F7: 850 | G7: 900 | H7: 950
A8: Work-in-Process ($M) | B8: 3800 | C8: 4000 | D8: 3800 | E8: 3600 | F8: 3500 | G8: 3600 | H8: 3800
A9: Finished Goods ($M) | B9: 3200 | C9: 3700 | D9: 3700 | E9: 3700 | F9: 3650 | G9: 4000 | H9: 4250
A10: Total Inventory ($M) | B10: =SUM(B7:B9) -> 8200 | C10: =SUM(C7:C9) -> 8800 | D10: =SUM(D7:D9) -> 8500 | E10: =SUM(E7:E9) -> 8200 | F10: =SUM(F7:F9) -> 8000 | G10: =SUM(G7:G9) -> 8500 | H10: =SUM(H7:H9) -> 9000
A12: DAYS INVENTORY OUTSTANDING (DIO)
A13: Quarterly COGS ($M) | B13: 4911 | C13: 6136 | D13: 5892 | E13: 6084 | F13: 6365 | G13: 7700 | H13: 8400
A14: Days Inventory Outstanding | B14: =B10/(B13/90) -> 150.27489 | C14: =C10/(C13/90) -> 129.07432 | D14: =D10/(D13/90) -> 129.83707 | E14: =E10/(E13/90) -> 121.30178 | F14: =F10/(F13/90) -> 113.11862 | G14: =G10/(G13/90) -> 99.350649 | H14: =H10/(H13/90) -> 96.428571
A15: DIO Signal | B15: NORMAL | C15: TIGHTENING | D15: TIGHT | E15: VERY TIGHT | F15: TIGHT | G15: NORMALIZING | H15: WATCH
A17: OTHER WORKING CAPITAL
A18: Accounts Receivable ($M) | B18: 4500 | C18: 5500 | D18: 6500 | E18: 10000 | F18: 13000 | G18: 14000 | H18: 12000
A19: Days Sales Outstanding (DSO) | B19: =B18/(B13+B18)/90*90 -> 0.47816385 | C19: =C18/(C13+C18)/90*90 -> 0.47267102 | D19: =D18/(D13+D18)/90*90 -> 0.52453196 | E19: =E18/(E13+E18)/90*90 -> 0.62173589 | F19: =F18/(F13+F18)/90*90 -> 0.67131423 | G19: =G18/(G13+G18)/90*90 -> 0.64516129 | H19: =H18/(H13+H18)/90*90 -> 0.58823529
A20: Accounts Payable ($M) | B20: 2800 | C20: 3200 | D20: 3500 | E20: 4500 | F20: 5500 | G20: 6000 | H20: 5500
A22: Net Working Capital ($M) | B22: =B10+B18-B20 -> 9900 | C22: =C10+C18-C20 -> 11100 | D22: =D10+D18-D20 -> 11500 | E22: =E10+E18-E20 -> 13700 | F22: =F10+F18-F20 -> 15500 | G22: =G10+G18-G20 -> 16500 | H22: =H10+H18-H20 -> 15500
A23: NWC Change QoQ (Cash Use if +) | C23: =C22-B22 -> 1200 | D23: =D22-C22 -> 400 | E23: =E22-D22 -> 2200 | F23: =F22-E22 -> 1800 | G23: =G22-F22 -> 1000 | H23: =H22-G22 -> -1000
A25: WATCH SIGNAL: DIO rising above 130 while ASPs flatten =...
A27: CASH CONVERSION CYCLE (CCC)
B28: FQ2-25 (A) | C28: FQ4-25 (A) | D28: FQ1-26 (A) | E28: FQ2-26 (A) | F28: FQ3-26E | G28: FQ4-26E | H28: FQ1-27E
A29: (+) Days Inventory Outstanding | B29: =B14 -> 150.27489 | C29: =C14 -> 129.07432 | D29: =D14 -> 129.83707 | E29: =E14 -> 121.30178 | F29: =F14 -> 113.11862 | G29: =G14 -> 99.350649 | H29: =H14 -> 96.428571
A30: (+) Days Sales Outstanding | B30: 50 | C30: 44 | D30: 43 | E30: 38 | F30: 35 | G30: 36 | H30: 38
A31: (-) Days Payable Outstanding | B31: 52 | C31: 48 | D31: 50 | E31: 55 | F31: 58 | G31: 55 | H31: 52
A32: CASH CONVERSION CYCLE (days) | B32: =B29+B30-B31 -> 148.27489 | C32: =C29+C30-C31 -> 125.07432 | D32: =D29+D30-D31 -> 122.83707 | E32: =E29+E30-E31 -> 104.30178 | F32: =F29+F30-F31 -> 90.118617 | G32: =G29+G30-G31 -> 80.350649 | H32: =H29+H30-H31 -> 82.428571
A34: HISTORICAL INVENTORY CYCLE CONTEXT
A35: Cycle Phase | B35: DIO Range | C35: Signal | D35: Price Direction | E35: Example Period
A36: Trough (Oversupply) | B36: 160-200+ days | C36: BEARISH — inventory glut | D36: Prices falling | E36: H2-2022 / H1-2023
A37: Early Recovery | B37: 130-160 days | C37: NEUTRAL — drawdown starting | D37: Prices stabilizing | E37: H2-2023
A38: Mid-Cycle Expansion | B38: 100-130 days | C38: BULLISH — healthy demand pull | D38: Prices rising | E38: H1-2024 / H2-2024
A39: Supply Shortage (Current) | B39: 80-100 days | C39: VERY BULLISH — rationing | D39: Prices surging | E39: H1-2025 → Current
A40: Peak Tightness | B40: <80 days | C40: CAUTION — unsustainably tight | D40: Peak pricing | E40: Rare; possible FQ3-26
A42: WORKING CAPITAL INTENSITY (NWC / Revenue)
A43: Quarterly Revenue ($M) | B43: 8050 | C43: 11300 | D43: 13640 | E43: 23860 | F43: 33500 | G43: 35000 | H43: 30000
A44: NWC / Revenue (%) | B44: =B22/B43 -> 1.2298137 | C44: =C22/C43 -> 0.98230088 | D44: =D22/D43 -> 0.8431085 | E44: =E22/E43 -> 0.57418273 | F44: =F22/F43 -> 0.46268657 | G44: =G22/G43 -> 0.47142857 | H44: =H22/H43 -> 0.51666667
A45: NWC / Revenue (Annualized) | B45: =B22/(B43*4) -> 0.30745342 | C45: =C22/(C43*4) -> 0.24557522 | D45: =D22/(D43*4) -> 0.21077713 | E45: =E22/(E43*4) -> 0.14354568 | F45: =F22/(F43*4) -> 0.11567164 | G45: =G22/(G43*4) -> 0.11785714 | H45: =H22/(H43*4) -> 0.12916667

Sheet Share Count Bridge
A1: SHARE COUNT BRIDGE
A2: Tracks dilution (RSUs/options) vs. buyback-driven reduction | Drives EPS denominator
A3: Circuit Breaker: Buyback share calc uses Assumptions!B59 price when toggle=0
B4: FQ1-26 (A) | C4: FQ2-26 (A) | D4: FQ3-26E | E4: FQ4-26E | F4: FQ1-27E | G4: FQ2-27E | H4: FQ3-27E | I4: FQ4-27E
A6: Basic Shares Outstanding (M) | B6: 1105 | C6: 1108 | D6: =C6+D8-D9 -> 1116.9 | E6: =D6+E8-E9 -> 1125.8 | F6: =E6+F8-F9 -> 1137.6 | G6: =F6+G8-G9 -> 1151.9 | H6: =G6+H8-H9 -> 1167.4 | I6: =H6+I8-I9 -> 1182.9
A7: SBC Dilution (new shares/qtr, M) | B7: 5 | C7: 5 | D7: 5 | E7: 5 | F7: 5 | G7: 5 | H7: 5 | I7: 5
A8: Total Dilutive Shares Added (M) | B8: 8 | C8: 8 | D8: 8 | E8: 8 | F8: 8 | G8: 8 | H8: 8 | I8: 8
A9: Buyback Shares Retired (M) | B9: -1.1 | C9: -1 | D9: -0.9 | E9: -0.9 | F9: -3.8 | G9: -6.3 | H9: -7.5 | I9: -7.5
A11: Diluted Shares Outstanding (M) | B11: 1140 | C11: 1142 | D11: =D6+35 -> 1151.9 | E11: =E6+35 -> 1160.8 | F11: =F6+35 -> 1172.6 | G11: =G6+35 -> 1186.9 | H11: =H6+35 -> 1202.4 | I11: =I6+35 -> 1217.9
A13: Check vs. Assumptions Tab | B13: =Assumptions!F26 -> 1138 | C13: =Assumptions!G26 -> 1142 | D13: =Assumptions!H26 -> 1145 | E13: =Assumptions!I26 -> 1148 | F13: =Assumptions!J26 -> 1140 | G13: =Assumptions!K26 -> 1130 | H13: =Assumptions!L26 -> 1118 | I13: =Assumptions!M26 -> 1105
A14: Variance (should be ~0) | B14: =B11-B13 -> 2 | C14: =C11-C13 -> 0 | D14: =D11-D13 -> 6.9 | E14: =E11-E13 -> 12.8 | F14: =F11-F13 -> 32.6 | G14: =G11-G13 -> 56.9 | H14: =H11-H13 -> 84.4 | I14: =I11-I13 -> 112.9
A16: BUYBACK CAPACITY ANALYSIS
A17: Annual FCF ($B) | B17: 35 | C17: 30
A18: CapEx ($B) | B18: -25 | C18: -39
A19: Dividends ($B) | B19: -0.65 | C19: -0.8
A20: Debt Service ($B) | B20: -2 | C20: -1
A21: Max Available for Buybacks ($B) | B21: =(B17+B18)*-1+B17+B19+B20+B17 -> 57.35 | C21: =(C17+C18)*-1+C17+C19+C20+C17 -> 67.2
A22: CHIPS Act Constraint | B22: ~$1.5B/yr limit until Dec 2026 | C22: Fully unconstrained post-Dec 2026
A24: POST-CHIPS RESTRICTION: Once buyback restrictions ease ...
A26: TREASURY STOCK METHOD — DILUTIVE SECURITIES DETAIL
A27: Security Type | B27: Shares Granted (M) | C27: Wtd Avg Exercise ($) | D27: In-the-Money at $366? | E27: Dilutive Shares (M) | F27: TSM Shares Added (M)
A28: Stock Options (outstanding) | B28: 12 | C28: 55 | D28: YES | E28: 12 | F28: =E28-E28*C28/366 -> 10.196721 | G28: Deep in-the-money; exercise price well below current
A29: RSUs (unvested) | B29: 18 | C29: 0 | D29: YES (always) | E29: 18 | F29: 18 | G29: RSUs always dilutive; no exercise price
A30: PSUs (performance-based) | B30: 5 | C30: 0 | D30: Conditional | E30: 3 | F30: 3 | G30: ~60% expected to vest based on current trajectory
A31: ESPP shares | B31: 3 | D31: YES | E31: 2 | F31: 2 | G31: Employee stock purchase plan; 15% discount
A32: Total Dilutive Securities (TSM) | F32: =SUM(F28:F31) -> 33.196721
A34: RSU VESTING SCHEDULE (Estimated)
B35: FQ3-26E | C35: FQ4-26E | D35: FQ1-27E | E35: FQ2-27E | F35: FQ3-27E | G35: FQ4-27E | H35: FY2027E Total
A36: RSUs Vesting (M shares) | B36: 4.5 | C36: 5 | D36: 4.5 | E36: 4 | F36: 4.5 | G36: 5 | H36: =SUM(D36:G36) -> 18
A37: SBC Expense ($M) | B37: =B36*150 -> 675 | C37: =C36*150 -> 750 | D37: =D36*150 -> 675 | E37: =E36*150 -> 600 | F37: =F36*150 -> 675 | G37: =G36*150 -> 750
A38: SBC as % of Revenue | B38: 0.02 | C38: 0.019 | D38: 0.022 | E38: 0.024 | F38: 0.025 | G38: 0.026
A40: EPS SENSITIVITY TO SHARE COUNT
A41: Diluted Shares (M) | B41: 1,095 | C41: 1,105 | D41: 1,115 | E41: 1,125 | F41: 1,135 | G41: 1,142 | H41: 1,150
A42: FY2027E Net Income ($B) | B42: 42
A43: Implied EPS ($) | B43: =B42*1000/1095 -> 38.356164 | C43: =B42*1000/1105 -> 38.00905 | D43: =B42*1000/1115 -> 37.668161 | E43: =B42*1000/1125 -> 37.333333 | F43: =B42*1000/1135 -> 37.004405 | G43: =B42*1000/1142 -> 36.777583 | H43: =B42*1000/1150 -> 36.521739
A44: EPS Impact vs Base (1,142M) | B44: =B43-F43 -> 1.3517591 | C44: =C43-F43 -> 1.0046445 | D44: =D43-F43 -> 0.66375615 | E44: =E43-F43 -> 0.32892805 | F44: =F43-F43 -> 0 | G44: =G43-F43 -> -0.2268221 | H44: =H43-F43 -> -0.48266616

Sheet DCF
A1: DISCOUNTED CASH FLOW MODEL
A2: 3-stage DCF: Explicit forecast (FY26-28) → Fade (FY29-31) → Terminal | WACC-based discounting
A4: WACC CALCULATION
A5: Risk-Free Rate (%) | B5: 0.042
A6: Equity Risk Premium (%) | B6: 0.055
A7: Beta (5-yr levered) | B7: 1.25
A8: Cost of Equity (%) | B8: =B5+B7*B6 -> 0.11075
A9: Pre-Tax Cost of Debt (%) | B9: 0.053
A10: Tax Rate (%) | B10: 0.151
A11: After-Tax Cost of Debt (%) | B11: =B9*(1-B10) -> 0.044997
A12: Debt / Total Capital (%) | B12: 0.024
A13: Equity / Total Capital (%) | B13: =1-B12 -> 0.976
A14: WACC (%) | B14: =B8*B13+B11*B12 -> 0.10917193
A16: FREE CASH FLOW PROJECTIONS ($B)
B17: FY2026E | C17: FY2027E | D17: FY2028E | E17: FY2029E | F17: FY2030E | G17: FY2031E
B18: Explicit | C18: Explicit | D18: Explicit | E18: Fade | F18: Fade | G18: Fade
A19: Revenue ($B) | B19: 106 | C19: 118 | D19: 105 | E19: 90 | F19: 88 | G19: 95
A20: EBITDA Margin (%) | B20: 0.75 | C20: 0.65 | D20: 0.55 | E20: 0.48 | F20: 0.45 | G20: 0.5
A21: EBITDA ($B) | B21: =B19*B20 -> 79.5 | C21: =C19*C20 -> 76.7 | D21: =D19*D20 -> 57.75 | E21: =E19*E20 -> 43.2 | F21: =F19*F20 -> 39.6 | G21: =G19*G20 -> 47.5
A22: (-) D&A ($B) | B22: -12 | C22: -15 | D22: -18 | E22: -20 | F22: -21 | G22: -21
A23: EBIT ($B) | B23: =B21+B22 -> 67.5 | C23: =C21+C22 -> 61.7 | D23: =D21+D22 -> 39.75 | E23: =E21+E22 -> 23.2 | F23: =F21+F22 -> 18.6 | G23: =G21+G22 -> 26.5
A24: (-) Taxes on EBIT | B24: =-B23*0.151 -> -10.1925 | C24: =-C23*0.151 -> -9.3167 | D24: =-D23*0.151 -> -6.00225 | E24: =-E23*0.151 -> -3.5032 | F24: =-F23*0.151 -> -2.8086 | G24: =-G23*0.151 -> -4.0015
A25: NOPAT ($B) | B25: =B23+B24 -> 57.3075 | C25: =C23+C24 -> 52.3833 | D25: =D23+D24 -> 33.74775 | E25: =E23+E24 -> 19.6968 | F25: =F23+F24 -> 15.7914 | G25: =G23+G24 -> 22.4985
A26: (+) D&A ($B) | B26: =-B22 -> 12 | C26: =-C22 -> 15 | D26: =-D22 -> 18 | E26: =-E22 -> 20 | F26: =-F22 -> 21 | G26: =-G22 -> 21
A27: (-) CapEx ($B) | B27: -25 | C27: -36 | D27: -32 | E27: -25 | F27: -22 | G27: -24
A28: (+) CHIPS Act Offsets ($B) | B28: 1.2 | C28: 1.2 | D28: 1.2 | E28: 1 | F28: 0.8 | G28: 0.5
A29: (-) Change in NWC ($B) | B29: -3 | C29: -2 | D29: 1 | E29: 1 | F29: 0.5 | G29: -0.5
A31: UNLEVERED FREE CASH FLOW ($B) | B31: =B25+B26+B27+B28+B29 -> 42.5075 | C31: =C25+C26+C27+C28+C29 -> 30.5833 | D31: =D25+D26+D27+D28+D29 -> 21.94775 | E31: =E25+E26+E27+E28+E29 -> 16.6968 | F31: =F25+F26+F27+F28+F29 -> 16.0914 | G31: =G25+G26+G27+G28+G29 -> 19.4985
A33: DISCOUNTED VALUES
A34: Discount Period (years) | B34: 0.5 | C34: 1.5 | D34: 2.5 | E34: 3.5 | F34: 4.5 | G34: 5.5
A35: Discount Factor | B35: =1/(1+B14)^B34 -> 0.94951224 | C35: =1/(1+B14)^C34 -> 0.85605505 | D35: =1/(1+B14)^D34 -> 0.77179654 | E35: =1/(1+B14)^E34 -> 0.69583129 | F35: =1/(1+B14)^F34 -> 0.62734304 | G35: =1/(1+B14)^G34 -> 0.56559585
A36: PV of FCF ($B) | B36: =B31*B35 -> 40.361391 | C36: =C31*C35 -> 26.180989 | D36: =D31*D35 -> 16.939197 | E36: =E31*E35 -> 11.618156 | F36: =F31*F35 -> 10.094828 | G36: =G31*G35 -> 11.028271
A37: Sum of PV of FCFs ($B) | B37: =SUM(B36:G36) -> 116.22283
A39: TERMINAL VALUE
A40: Terminal FCF (FY2031E, $B) | B40: =G31 -> 19.4985
A41: Terminal Growth Rate (%) | B41: 0.035
A42: Terminal Value ($B) | B42: =B40*(1+B41)/(B14-B41) -> 272.08336
A43: PV of Terminal Value ($B) | B43: =B42*G35 -> 153.88922
A44: Implied Terminal EV/EBITDA | B44: =B42/G21 -> 5.7280708
A46: ENTERPRISE TO EQUITY VALUE BRIDGE
A47: Sum of PV of FCFs ($B) | B47: =B37 -> 116.22283
A48: PV of Terminal Value ($B) | B48: =B43 -> 153.88922
A49: Enterprise Value ($B) | B49: =B47+B48 -> 270.11205
A50: (-) Net Debt / (+) Net Cash ($B) | B50: 6.6
A51: Equity Value ($B) | B51: =B49+B50 -> 276.71205
A52: Diluted Shares (B) | B52: 1.142
A53: DCF FAIR VALUE PER SHARE | B53: =B51/B52 -> 242.30478
A54: Current Price | B54: 366
A55: Implied Upside / (Downside) | B55: =(B53-B54)/B54 -> -0.33796509
A57: DCF SENSITIVITY: WACC vs Terminal Growth
A58: Terminal Growth → | B58: 0.02 | C58: 0.025 | D58: 0.03 | E58: 0.035 | F58: 0.04 | G58: 0.045 | H58: 0.05
A59: WACC 8.0% | B59: 412 | C59: 440 | D59: 474 | E59: 515 | F59: 567 | G59: 633 | H59: 722
A60: WACC 9.0% | B60: 358 | C60: 377 | D60: 400 | E60: 427 | F60: 460 | G60: 499 | H60: 549
A61: WACC 10.0% | B61: 318 | C61: 332 | D61: 348 | E61: 367 | F61: 389 | G61: 415 | H61: 446
A62: WACC 10.5% | B62: 302 | C62: 314 | D62: 328 | E62: 344 | F62: 362 | G62: 384 | H62: 409
A63: WACC 11.0% | B63: 287 | C63: 298 | D63: 310 | E63: 324 | F63: 339 | G63: 358 | H63: 379
A64: WACC 12.0% | B64: 263 | C64: 272 | D64: 281 | E64: 291 | F64: 303 | G64: 316 | H64: 331
A65: WACC 13.0% | B65: 244 | C65: 251 | D65: 258 | E65: 266 | F65: 275 | G65: 285 | H65: 296
A67: SCENARIO-SPECIFIC DCF VALUES
A68: Scenario | B68: Probability | C68: Rev CAGR (FY26-31) | D68: Avg EBITDA Margin | E68: Terminal Growth | F68: DCF Fair Value | G68: vs Current
A69: AI Supercycle (Bull) | B69: 0.25 | C69: 0.05 | D69: 0.62 | E69: 0.045 | F69: 750 | G69: =(F69-366)/366 -> 1.0491803
A70: Steady Growth (Base) | B70: 0.45 | C70: 0 | D70: 0.52 | E70: 0.035 | F70: 520 | G70: =(F70-366)/366 -> 0.42076503
A71: Cyclical Correction | B71: 0.2 | C71: -0.05 | D71: 0.42 | E71: 0.03 | F71: 300 | G71: =(F71-366)/366 -> -0.18032787
A72: Hard Landing | B72: 0.1 | C72: -0.12 | D72: 0.32 | E72: 0.02 | F72: 140 | G72: =(F72-366)/366 -> -0.61748634
A73: PROB-WEIGHTED DCF VALUE | F73: =SUMPRODUCT(B69:B72,F69:F72) -> 495.5 | G73: =(F73-366)/366 -> 0.35382514
A75: FCFF vs FCFE RECONCILIATION (FY2026E)
A77: Net Income ($B) | B77: 55
A78: (+) D&A ($B) | B78: 11
A79: (-) CapEx ($B) | B79: -25
A80: (+) CHIPS Act Offsets ($B) | B80: 1.2
A81: (-) Change in NWC ($B) | B81: -3
A82: Free Cash Flow to Equity (FCFE, $B) | B82: =SUM(B77:B81) -> 39.2
A83: (+) Interest Expense x (1-t) ($B) | B83: 0.4
A84: (-) Net Debt Repayment ($B) | B84: -3.5
A85: Free Cash Flow to Firm (FCFF, $B) | B85: =B82+B83+B84 -> 36.1
A87: FOOTBALL FIELD VALUATION SUMMARY
A88: Methodology | B88: Low ($) | C88: Base ($) | D88: High ($) | E88: Current ($366)
A89: DCF (WACC 9-12%) | B89: 300 | C89: 520 | D89: 750 | E89: 366
A90: NTM P/E (10-18x) | B90: 350 | C90: 520 | D90: 750 | E90: 366
A91: Mid-Cycle P/E (10-18x) | B91: 280 | C91: 450 | D91: 630 | E91: 366
A92: EV/EBITDA (8-14x) | B92: 320 | C92: 480 | D92: 700 | E92: 366
A93: FCF Yield (4-8%) | B93: 380 | C93: 510 | D93: 760 | E93: 366
A94: Sum-of-Parts | B94: 350 | C94: 520 | D94: 700 | E94: 366
A95: Prob-Weighted Scenarios | B95: 250 | C95: 490 | D95: 750 | E95: 366
A96: COMPOSITE RANGE | B96: =MIN(B89:B95) -> 250 | C96: =AVERAGE(C89:C95) -> 498.57143 | D96: =MAX(D89:D95) -> 760
A97: % vs Current ($366) | B97: =(B96-366)/366 -> -0.31693989 | C97: =(C96-366)/366 -> 0.36221702 | D97: =(D96-366)/366 -> 1.0765027
A99: EXTERNAL DCF REFERENCE: BEATING THE TIDE ($934 PT)
A100: Assumption | B100: Their Value | C100: Our Value | D100: Delta
A101: WACC | B101: 9.6% | C101: ~10.9% | D101: We're more conservative
A102: FY2026E Revenue | B102: ~$109B | C102: $106B | D102: Close
A103: GM Floor (structural) | B103: 65-81% | C103: 70% FY26 blended | D103: They use wider range
A104: SG&A % of Rev | B104: 1.4% | C104: ~1.8% | D104: Close
A105: Tax Rate | B105: 17% | C105: 15.1% | D105: We're lower (FQ2 actual)
A106: FY2026 CapEx | B106: >$25B | C106: $25B | D106: Same
A107: Terminal Growth | B107: Not disclosed | C107: 3.5% | D107: N/A
A108: Result | B108: $934/share | C108: ~$520 base | D108: Their WACC 130bps lower = huge TV difference

Sheet Valuation
A1: MICRON TECHNOLOGY — MULTI-METHODOLOGY VALUATION
A2: Current Price: $366 | As of April 5, 2026
A4: CURRENT MARKET DATA
A5: Share Price ($) | B5: 366
A6: Diluted Shares (M) | B6: 1142
A7: Market Cap ($B) | B7: =B5*B6/1000 -> 417.972
A8: Total Debt ($B) | B8: 10.1
A9: Cash & Investments ($B) | B9: 16.7
A10: Enterprise Value ($B) | B10: =B7+B8-B9 -> 411.372
A12: VALUATION METHODOLOGIES
A13: Methodology | B13: Metric | C13: Multiple | D13: Implied Price | E13: vs Current
A14: 1. LTM P/E | B14: LTM EPS (FQ3-25 thru FQ2-26) | C14: ='Historical P&L'!D35+'Historical P&L'!E35+'Historical P&L'!F35+'Historical P&L'!G35 -> 21.92 | D14: =B5/C14 -> 16.69708
A15: 2. NTM P/E (FY2026E) | B15: FY2026E EPS | C15: ='Projected P&L'!H33 -> 54.939418 | D15: 14 | E15: =C15*D15 -> 769.15185 | F15: =(E15-B5)/B5 -> 1.1015078
A16: 3. FY2027E P/E | B16: FY2027E EPS | C16: ='Projected P&L'!I33 -> 53.52243 | D16: 12 | E16: =C16*D16 -> 642.26916 | F16: =(E16-B5)/B5 -> 0.75483378
A17: 4. Mid-Cycle P/E | B17: Mid-Cycle EPS (avg FY25-27) | C17: =('Historical P&L'!H35+'Projected P&L'!H33+'Projected P&L'!I33)/3 -> 38.917283 | D17: 15 | E17: =C17*D17 -> 583.75924 | F17: =(E17-B5)/B5 -> 0.5949706
A18: 5. EV/EBITDA (FY2026E) | B18: FY2026E EBITDA ($B) | C18: 85 | D18: 11 | E18: =(C18*D18-B8+B9)*1000/B6 -> 824.51839 | F18: =(E18-B5)/B5 -> 1.2527825
A19: 6. FCF Yield | B19: FY2026E FCF ($B) | C19: 35 | D19: 0.06 | E19: =C19/D19*1000/B6 -> 510.79977 | F19: =(E19-B5)/B5 -> 0.39562778
A20: 7. Sum-of-Parts | B20: DRAM + NAND + HBM | E20: 520 | F20: =(E20-B5)/B5 -> 0.42076503
A22: SCENARIO-WEIGHTED VALUATION
A23: Scenario | B23: Probability | C23: FY27E EPS | D23: Fair P/E | E23: Target Price | F23: Contribution
A24: AI Supercycle (Bull) | B24: =Assumptions!B30 -> 0.25 | C24: =Assumptions!B42 -> 60 | D24: =Assumptions!B36 -> 16 | E24: =C24*D24 -> 960 | F24: =B24*E24 -> 240
A25: Steady Growth (Base) | B25: =Assumptions!B31 -> 0.45 | C25: =Assumptions!B43 -> 48 | D25: =Assumptions!B37 -> 12 | E25: =C25*D25 -> 576 | F25: =B25*E25 -> 259.2
A26: Cyclical Correction (Bear) | B26: =Assumptions!B32 -> 0.2 | C26: =Assumptions!B44 -> 30 | D26: =Assumptions!B38 -> 8 | E26: =C26*D26 -> 240 | F26: =B26*E26 -> 48
A27: Hard Landing | B27: =Assumptions!B33 -> 0.1 | C27: =Assumptions!B45 -> 12 | D27: =Assumptions!B39 -> 6 | E27: =C27*D27 -> 72 | F27: =B27*E27 -> 7.2
A28: PROBABILITY-WEIGHTED TARGET | F28: =SUM(F24:F27) -> 554.4
A29: Implied Upside / (Downside) | F29: =(F28-B5)/B5 -> 0.5147541
A31: WHAT THE MARKET IS PRICING IN (BACK-SOLVE)
A32: Current Price at 14x P/E implies EPS of: | B32: =B5/14 -> 26.142857
A33: Current Price at 10x P/E implies EPS of: | B33: =B5/10 -> 36.6
A34: Current Price at 7x P/E implies EPS of: | B34: =B5/7 -> 52.285714
A36: SENSITIVITY TABLE: FY27E EPS vs P/E MULTIPLE
A37: FY27E EPS → | B37: 20 | C37: 25 | D37: 30 | E37: 35 | F37: 40 | G37: 42 | H37: 45 | I37: 50 | J37: 55
A38: 7x P/E | B38: 140 | C38: 175 | D38: 210 | E38: 245 | F38: 280 | G38: 294 | H38: 315 | I38: 350 | J38: 385
A39: 8x P/E | B39: 160 | C39: 200 | D39: 240 | E39: 280 | F39: 320 | G39: 336 | H39: 360 | I39: 400 | J39: 440
A40: 10x P/E | B40: 200 | C40: 250 | D40: 300 | E40: 350 | F40: 400 | G40: 420 | H40: 450 | I40: 500 | J40: 550
A41: 12x P/E | B41: 240 | C41: 300 | D41: 360 | E41: 420 | F41: 480 | G41: 504 | H41: 540 | I41: 600 | J41: 660
A42: 14x P/E | B42: 280 | C42: 350 | D42: 420 | E42: 490 | F42: 560 | G42: 588 | H42: 630 | I42: 700 | J42: 770
A43: 15x P/E | B43: 300 | C43: 375 | D43: 450 | E43: 525 | F43: 600 | G43: 630 | H43: 675 | I43: 750 | J43: 825
A44: 16x P/E | B44: 320 | C44: 400 | D44: 480 | E44: 560 | F44: 640 | G44: 672 | H44: 720 | I44: 800 | J44: 880
A45: 18x P/E | B45: 360 | C45: 450 | D45: 540 | E45: 630 | F45: 720 | G45: 756 | H45: 810 | I45: 900 | J45: 990
A46: 20x P/E | B46: 400 | C46: 500 | D46: 600 | E46: 700 | F46: 800 | G46: 840 | H46: 900 | I46: 1000 | J46: 1100
A48: WALL STREET CONSENSUS ESTIMATES
B49: FY2026E | C49: FY2027E | D49: FY2028E | E49: Source
A50: Revenue ($B) | B50: 106 | C50: 118.5 | D50: 105 | E50: StockAnalysis / BofA post-Q2
A51: Revenue YoY Growth | B51: =B50/37.4-1 -> 1.8342246 | C51: =C50/B50-1 -> 0.11792453 | D51: =D50/C50-1 -> -0.11392405
A52: Non-GAAP EPS (consensus) | B52: 35.27 | C52: 48.07 | D52: 29.15 | E52: StockAnalysis mean; FY28 = BofA
A53: EPS Range (low) | B53: 27.85 | C53: 27.89 | D53: From Projected P&L tab | E53: StockAnalysis range
A54: EPS Range (high) | B54: 47.99 | C54: 79.76 | D54: 38 Buy, 0 Hold, 0 Sell | E54: StockAnalysis range
A55: Gross Margin (est.) | B55: 0.7 | C55: 0.6 | D55: 0.48 | E55: Blended full-year; H2-26 peak ~81%
A56: CapEx ($B) | B56: 25 | C56: 36 | D56: 32 | E56: Mgmt: >$25B FY26; +$10B FY27 construction
A57: FCF ($B) | B57: 35 | C57: 30 | D57: 25 | E57: OCF minus capex; FQ3 FCF guide 'roughly double' $6.9B
A58: Analyst Count | B58: 38 Buy / 0 Sell | E58: StockAnalysis April 2026
A59: Avg Price Target ($) | B59: 492 | C59: Rating | D59: Target ($) | E59: StockAnalysis; range $400 (GS) to $700 (Cantor)
A60: Cantor Fitzgerald | C60: Buy | D60: 700 | E60: Mar 26 | F60: Expects 'very aggressive' buybacks Dec 26+
A61: BOFA EPS TRAJECTORY (Most Detailed Bank Model) | B61: Srini Pajjuri | C61: Outperform | D61: 525 | E61: Mar 26 | F61: HBM TAM + contracted revenue quality
A62: BofA FY2026E EPS | B62: 31.84 | C62: Buy | D62: 500 | E62: Mar 26 | F62: AI memory supercycle duration
A63: BofA FY2027E EPS | B63: 38.85 | C63: Outperform | D63: 500 | E63: Mar 26 | F63: Raised from $320; structural shift
A64: BofA FY2028E EPS | B64: 29.15 | C64: Overweight | D64: 470 | E64: Mar 26 | F64: HBM + data center dominance
A65: Citi | B65: Atif Malik | C65: Buy | D65: 425 | E65: Apr 2 | F65: CUT from $510. TurboQuant + DDR5 spot
A66: BofA | C66: Buy | E66: Mar 26 | F66: Flagged HBM price risk in 2027

Sheet ROIC Analysis
A1: RETURN ON INVESTED CAPITAL (ROIC) ANALYSIS
A2: ROIC measures capital efficiency through the cycle | ROIC > WACC = value creation
B4: FY2023 (A) | C4: FY2024 (A) | D4: FY2025 (A) | E4: FY2026E | F4: FY2027E | G4: FY2028E
A6: NOPAT (Net Operating Profit After Tax)
A7: Revenue ($B) | B7: 15.5 | C7: 25.1 | D7: 37.4 | E7: 106 | F7: 118 | G7: 105
A8: Operating Income ($B) | B8: -5.7 | C8: 1.5 | D8: 9.5 | E8: 68 | F8: 62 | G8: 40
A9: Operating Margin (%) | B9: =B8/B7 -> -0.36774194 | C9: =C8/C7 -> 0.059760956 | D9: =D8/D7 -> 0.2540107 | E9: =E8/E7 -> 0.64150943 | F9: =F8/F7 -> 0.52542373 | G9: =G8/G7 -> 0.38095238
A10: Tax Rate (%) | B10: 0.151 | C10: 0.151 | D10: 0.151 | E10: 0.151 | F10: 0.151 | G10: 0.151
A11: NOPAT ($B) | B11: =B8*(1-B10) -> -4.8393 | C11: =C8*(1-C10) -> 1.2735 | D11: =D8*(1-D10) -> 8.0655 | E11: =E8*(1-E10) -> 57.732 | F11: =F8*(1-F10) -> 52.638 | G11: =G8*(1-G10) -> 33.96
A13: INVESTED CAPITAL
A14: Net PP&E ($B) | B14: 34 | C14: 36 | D14: 40 | E14: 55 | F14: 73 | G14: 85
A15: Net Working Capital ($B) | B15: 6 | C15: 7 | D15: 8 | E15: 12 | F15: 14 | G15: 13
A16: Other Operating Assets ($B) | B16: 4 | C16: 4 | D16: 5 | E16: 6 | F16: 7 | G16: 7
A17: Invested Capital ($B) | B17: =B14+B15+B16 -> 44 | C17: =C14+C15+C16 -> 47 | D17: =D14+D15+D16 -> 53 | E17: =E14+E15+E16 -> 73 | F17: =F14+F15+F16 -> 94 | G17: =G14+G15+G16 -> 105
A19: RETURN ON INVESTED CAPITAL
A20: ROIC (%) | B20: =B11/B17 -> -0.10998409 | C20: =C11/C17 -> 0.027095745 | D20: =D11/D17 -> 0.15217925 | E20: =E11/E17 -> 0.79084932 | F20: =F11/F17 -> 0.55997872 | G20: =G11/G17 -> 0.32342857
A21: WACC (%) | B21: =DCF!B14 -> 0.10917193 | C21: =DCF!B14 -> 0.10917193 | D21: =DCF!B14 -> 0.10917193 | E21: =DCF!B14 -> 0.10917193 | F21: =DCF!B14 -> 0.10917193 | G21: =DCF!B14 -> 0.10917193
A22: ROIC - WACC Spread (Value Creation) | B22: =B20-B21 -> -0.21915602 | C22: =C20-C21 -> -0.082076183 | D22: =D20-D21 -> 0.043007317 | E22: =E20-E21 -> 0.68167739 | F22: =F20-F21 -> 0.4508068 | G22: =G20-G21 -> 0.21425664
A23: Invested Capital Turns (Revenue/IC) | B23: =B7/B17 -> 0.35227273 | C23: =C7/C17 -> 0.53404255 | D23: =D7/D17 -> 0.70566038 | E23: =E7/E17 -> 1.4520548 | F23: =F7/F17 -> 1.2553191 | G23: =G7/G17 -> 1
A25: THROUGH-CYCLE ROIC CONTEXT
A26: Average ROIC (FY23-28E) | B26: =AVERAGE(B20:G20) -> 0.29059125
A27: Peak ROIC (FY2026E) | B27: =MAX(B20:G20) -> 0.79084932
A28: Trough ROIC (FY2023) | B28: =MIN(B20:G20) -> -0.10998409
A29: ROIC Volatility (Std Dev) | B29: =STDEV(B20:G20) -> 0.33851275
A31: KEY INSIGHT: The swing from -11% ROIC (FY2023 trough) t...
A33: DUPONT DECOMPOSITION OF ROIC
A34: NOPAT Margin (%) | B34: =B11/B7 -> -0.3122129 | C34: =C11/C7 -> 0.050737052 | D34: =D11/D7 -> 0.21565508 | E34: =E11/E7 -> 0.54464151 | F34: =F11/F7 -> 0.44608475 | G34: =G11/G7 -> 0.32342857
A35: Capital Turns (x) | B35: =B23 -> 0.35227273 | C35: =C23 -> 0.53404255 | D35: =D23 -> 0.70566038 | E35: =E23 -> 1.4520548 | F35: =F23 -> 1.2553191 | G35: =G23 -> 1
A36: ROIC (Margin x Turns, check) | B36: =B34*B35 -> -0.10998409 | C36: =C34*C35 -> 0.027095745 | D36: =D34*D35 -> 0.15217925 | E36: =E34*E35 -> 0.79084932 | F36: =F34*F35 -> 0.55997872 | G36: =G34*G35 -> 0.32342857
A38: DUPONT INSIGHT: Micron's ROIC is almost entirely margin...
A40: INCREMENTAL ROIC (Marginal Returns on New Capital)
B41: FY24→25 | C41: FY25→26E | D41: FY26→27E | E41: FY27→28E
A42: Change in NOPAT ($B) | B42: 6.8 | C42: 49.6 | D42: -5.1 | E42: -18.6
A43: Change in Invested Capital ($B) | B43: 6 | C43: 17 | D43: 21 | E43: 11
A44: INCREMENTAL ROIC (%) | B44: =B42/B43 -> 1.1333333 | C44: =C42/C43 -> 2.9176471 | D44: =D42/D43 -> -0.24285714 | E44: =E42/E43 -> -1.6909091
A45: Incremental ROIC Signal | B45: STRONG | C45: EXTRAORDINARY | D45: NEGATIVE (cycle norm.) | E45: NEGATIVE (cycle turn)
A47: Incremental ROIC turning negative in FY26→27E and FY27→...
A49: ECONOMIC VALUE ADDED (EVA)
B50: FY2023 (A) | C50: FY2024 (A) | D50: FY2025 (A) | E50: FY2026E | F50: FY2027E | G50: FY2028E
A51: NOPAT ($B) | B51: -5 | C51: 1.3 | D51: 8.4 | E51: 57.7 | F51: 52.6 | G51: 34
A52: Invested Capital ($B) | B52: 44 | C52: 47 | D52: 53 | E52: 72 | F52: 94 | G52: 105
A53: Capital Charge (IC x WACC, $B) | B53: =B52*DCF!$B$14 -> 4.8035648 | C53: =C52*DCF!$B$14 -> 5.1310806 | D53: =D52*DCF!$B$14 -> 5.7861122 | E53: =E52*DCF!$B$14 -> 7.8603788 | F53: =F52*DCF!$B$14 -> 10.262161 | G53: =G52*DCF!$B$14 -> 11.463052
A54: EVA = NOPAT - Capital Charge ($B) | B54: =B51-B53 -> -9.8035648 | C54: =C51-C53 -> -3.8310806 | D54: =D51-D53 -> 2.6138878 | E54: =E51-E53 -> 49.839621 | F54: =F51-F53 -> 42.337839 | G54: =G51-G53 -> 22.536948
A55: Cumulative EVA ($B) | B55: =B54 -> -9.8035648 | C55: =B55+C54 -> -13.634645 | D55: =C55+D54 -> -11.020758 | E55: =D55+E54 -> 38.818864 | F55: =E55+F54 -> 81.156702 | G55: =F55+G54 -> 103.69365
A57: PEER ROIC COMPARISON
A58: Company | B58: FY2023 ROIC | C58: FY2024 ROIC | D58: FY2025 ROIC | E58: Avg ROIC (3yr) | F58: ROIC Vol (Std Dev) | G58: Quality Rating
A59: Micron (MU) | B59: -0.11 | C59: 0.03 | D59: 0.16 | E59: =AVERAGE(B59:D59) -> 0.026666667 | F59: =STDEV(B59:D59) -> 0.13503086 | G59: VOLATILE
A60: SK Hynix | B60: -0.08 | C60: 0.12 | D60: 0.55 | E60: =AVERAGE(B60:D60) -> 0.19666667 | F60: =STDEV(B60:D60) -> 0.32192132 | G60: VOLATILE
A61: Samsung (Memory) | B61: -0.05 | C61: 0.02 | D61: 0.12 | E61: =AVERAGE(B61:D61) -> 0.03 | F61: =STDEV(B61:D61) -> 0.085440037 | G61: VOLATILE
A62: NVIDIA (for context) | B62: 0.45 | C62: 0.8 | D62: 1.2 | E62: =AVERAGE(B62:D62) -> 0.81666667 | F62: =STDEV(B62:D62) -> 0.37527767 | G62: HIGH & STABLE
A63: TSMC (for context) | B63: 0.22 | C63: 0.28 | D63: 0.32 | E63: =AVERAGE(B63:D63) -> 0.27333333 | F63: =STDEV(B63:D63) -> 0.05033223 | G63: HIGH & STABLE
A65: Memory ROIC is inherently volatile due to commodity pri...

Sheet Comps
A1: COMPARABLE COMPANY ANALYSIS
A3: FINANCIAL COMPARISON (Latest Available)
A4: Metric | B4: Micron (MU) | C4: SK Hynix | D4: Samsung (Memory) | E4: Kioxia | F4: WDC (NAND)
A5: Market Cap ($B) | B5: 418 | C5: 120 | D5: 350 | E5: 15 | F5: 20
A6: FY Rev ($B, latest) | B6: 37.4 | C6: 67 | D6: 233 | E6: 12 | F6: 13
A7: FY Op. Margin (%) | B7: 0.41 | C7: 0.49 | D7: 0.13 | E7: 0.08 | F7: 0.1
A8: Gross Margin (latest Q) | B8: 0.745 | C8: 0.58 | D8: 0.58 | E8: 0.25 | F8: 0.3
A9: HBM Market Share (%) | B9: 0.21 | C9: 0.62 | D9: 0.22 | E9: 0 | F9: 0
A10: DRAM Market Share (%) | B10: 0.23 | C10: 0.33 | D10: 0.38 | E10: 0 | F10: 0
A11: NAND Market Share (%) | B11: 0.12 | C11: 0.21 | D11: 0.35 | E11: 0.14 | F11: 0.13
A12: Forward P/E (est.) | B12: 4.1 | C12: 6.5 | D12: 12 | F12: 15
A13: EV/EBITDA (est.) | B13: 11.1 | C13: 5.5 | D13: 9 | F13: 8
A16: TECHNOLOGY POSITIONING
A17: Capability | B17: Micron | C17: SK Hynix | D17: Samsung
A18: Leading DRAM Node | B18: 1-gamma (EUV) | C18: 1b (DUV) | D18: 1b (transition to EUV)
A19: NAND Layer Count | B19: 232L / 300L | C19: 321L (Solidigm) | D19: 290L V-NAND
A20: HBM Gen Shipping | B20: HBM4 12-hi (volume) | C20: HBM3E 12-hi (HBM4 sampling) | D20: HBM3E (HBM4 sampling)
A21: HBM4 Volume Status | B21: CQ1-2026 volume start | C21: Sampling to customers | D21: Sampling; yield challenges
A22: Key Technology Edge | B22: 1-gamma yield leadership; HBM4 first | C22: HBM scale & customer lock-in | D22: Foundry integration; scale
A23: Gov't Subsidies (US) | B23: $6.4B CHIPS Act grants | C23: None (Korea subsidies) | D23: None (Korea subsidies)
A24: Geographic Risk | B24: Taiwan (25% of DRAM) | C24: Korea (geopolitical) | D24: Korea + China

Sheet Risks & Catalysts
A1: RISK MATRIX & CATALYST CALENDAR
A3: RISK MATRIX
A4: Risk Factor | B4: Probability | C4: EPS Impact | D4: Monitoring Signal | E4: Mitigation Factor | F4: Severity
A5: Samsung closes HBM yield gap | B5: 0.25 | C5: -15 to -25% | D5: Samsung HBM3E/4 qualification at NVIDIA; TrendForce HBM share data | E5: Micron has 18-month technology lead on HBM4; customer switching costs high | F5: HIGH
A6: Taiwan Strait escalation | B6: 0.08 | C6: -30 to -40% | D6: US-China military posturing; Taiwan election dynamics; Pentagon assessments | E6: Diversification to Idaho/NY/India reduces concentration; 18mo inventory buffer | F6: CRITICAL
A7: Hyperscaler CapEx cliff | B7: 0.15 | C7: -20 to -30% | D7: Quarterly capex guidance from MSFT, GOOGL, AMZN, META; cloud... | E7: AI training demand is multi-year; inference demand growing; ... | F7: HIGH
A8: YMTC NAND capacity surge | B8: 0.3 | C8: -5 to -10% | D8: YMTC wafer starts data; China NAND pricing in channel | E8: US export controls limit YMTC to 128L; Micron NAND only 21% of rev | F8: MEDIUM
A9: NVIDIA shifts HBM allocation | B9: 0.1 | C9: -10 to -15% | D9: NVIDIA supplier qualification updates; competitive HBM benchmark results | E9: 5-year SCA signed; multi-customer base reduces single-customer risk | F9: MEDIUM
A10: EUV cost overruns (1-delta) | B10: 0.2 | C10: -5 to -8% | D10: ASML delivery schedules; Micron capex guidance revisions; peer cost data | E10: 1-gamma transition on track (fastest ever); 1-delta is CY2028+ risk | F10: LOW-MED
A11: Memory cycle peaks early | B11: 0.2 | C11: -15 to -20% | D11: DRAM contract pricing (TrendForce monthly); inventory days rising above 130 | E11: HBM contracted revenue creates floor; this cycle is structurally different | F11: MEDIUM
A12: Tariff / trade policy disruption | B12: 0.15 | C12: -5 to -10% | D12: US trade policy announcements; Section 301 updates; reciprocal tariffs | E12: CHIPS Act domestic investment partially hedges; diversified customer base | F12: MEDIUM
A15: CATALYST CALENDAR (April 2026 — March 2027)
A16: Date | B16: Event | C16: Expected Impact | D16: Materiality | E16: Direction
A17: Apr 15, 2026 | B17: Dividend record date ($0.15/qtr) | C17: Confirms capital return commitment | D17: Low | E17: Positive
A18: Apr-May 2026 | B18: Samsung CQ1-2026 earnings | C18: Reveals competitor HBM progress & pricing | D18: High | E18: Mixed
A19: Apr-May 2026 | B19: SK Hynix CQ1-2026 earnings | C19: Industry DRAM/HBM supply data | D19: High | E19: Mixed
A20: Jun 2026 | B20: MU FQ3-26 earnings (~Jun 18) | C20: Validation of $33.5B/$19.15 guidance | D20: Critical | E20: Positive
A21: Jul 2026 | B21: NVIDIA Vera Rubin architecture details | C21: HBM4 demand validation | D21: High | E21: Positive
A22: Aug 2026 | B22: TrendForce CQ3 DRAM contract pricing | C22: Leading indicator of pricing direction | D22: High | E22: Mixed
A23: Sep 2026 | B23: MU FQ4-26 earnings (~Sep 18) | C23: Full FY2026 results; FY2027 initial outlook | D23: Critical | E23: Mixed
A24: Oct-Dec 2026 | B24: CHIPS Act buyback restrictions ease | C24: Capital return acceleration potential | D24: Medium | E24: Positive
A25: H2 2027 | B25: Idaho Fab 1 wafer output begins | C25: First major US greenfield capacity addition | D25: High | E25: Positive
A26: CY2027 | B26: HBM4E volume ramp | C26: Next-gen HBM with higher ASP potential | D26: High | E26: Positive
A27: CY2027 | B27: Singapore HBM packaging contribution | C27: Supply capacity expansion for HBM | D27: Medium | E27: Positive
A29: NEW CATALYSTS FROM APRIL 2026 INTELLIGENCE
A30: Date | B30: Event | C30: Impact | D30: Materiality | E30: Direction
A31: Apr 5, 2026 | B31: Samsung +30% Q2 DRAM pricing confirmed | C31: Validates pricing power; Micron/SKH to follow | D31: High | E31: Positive
A32: Apr-May 2026 | B32: MS-SK Hynix DDR5 LTA finalization | C32: Sets industry precedent for contracted commodity DRAM | D32: Critical | E32: Positive
A33: Apr-May 2026 | B33: Samsung-Google/MS LTA negotiations | C33: Could shift from spot to contracted pricing paradigm | D33: Critical | E33: Positive
A34: Q3 2026 | B34: Key inflection point per etnews | C34: Big 3 capacity not yet expanded; AI demand decisive | D34: High | E34: Mixed
A35: CY2027 | B35: Micron stacked GDDR samples | C35: New product category between DDR5 and HBM | D35: Medium | E35: Positive
A37: SEMIANALYSIS CONTRARIAN RISK SIGNALS
A38: Signal | B38: Current Status | C38: Bear Implication | D38: Probability | E38: Source
A39: Memory ETF launch | B39: New memory-focused ETF launched | C39: Potential contrarian peak indicator; retail flows signal froth | D39: 0.15 | E39: SemiAnalysis / ainvest
A40: DRAM inventory > 10 weeks | B40: Currently ~8 weeks | C40: Would signal demand softening; watch quarterly | D40: 0.1 | E40: SemiAnalysis
A41: Cancel-to-book ratio rising | B41: Currently very low | C41: Hyperscalers canceling orders = demand cliff risk | D41: 0.1 | E41: SemiAnalysis monitoring signal
A42: Fab announcements >20 new | B42: Currently manageable | C42: 1993 parallel: 50 fab plans announced -> oversupply by 1996 | D42: 0.05 | E42: SemiAnalysis historical comparison
A43: Apple production restrictions | B43: Signaled potential CY2026 cuts | C43: Consumer DRAM demand destruction; less relevant for MU (exited consumer) | D43: 0.25 | E43: ainvest / industry reports
A45: CRITICAL NEW RISKS (April 2026 Intelligence)
A46: Risk Factor | B46: Probability | C46: EPS Impact | D46: Monitoring Signal | E46: Mitigation
A47: HBM4 Vera Rubin exclusion | B47: 0.6 | C47: -8 to -12% | D47: TrendForce 3/9/26: Samsung (30%) + SK Hynix (70%) tapped as ... | E47: Micron positioned for Rubin CPX + future rotation. HBM4 qual...
A48: Google TurboQuant algorithm | B48: 0.2 | C48: -15 to -25% (2028+) | D48: Memory compression could reduce LLM memory needs by up to 6x... | E48: Impacts inference > training. Near-term (FY26-27) training d...
A49: April 2 reciprocal tariffs | B49: 0.3 | C49: -2 to -5% | D49: Universal 10% tariff on imports from Taiwan/Japan/Singapore.... | E49: Micron imposing surcharge on modules/SSDs (DCD 4/9/26). CHIP...
A50: DDR5 spot price divergence | B50: 0.35 | C50: -3 to -8% | D50: DDR5 16Gb spot: -5.1% late March (Seoul Econ Daily). Middle ... | E50: Spot =/= contract. Micron sells to enterprise under contract...
A51: Capex 'hog cycle' overshoot | B51: 0.25 | C51: -10 to -20% (FY28+) | D51: FY26 capex $25B+. FY27 'stepping up meaningfully' (+$10B YoY... | E51: Historical parallel: 1993 had 50 fab announcements before ov...

Sheet Thesis Summary
A1: MICRON TECHNOLOGY ($MU) — INVESTMENT THESIS
A3: RECOMMENDATION: BUY — HIGH CONVICTION
A4: Target Price (Probability-Weighted): | B4: =Assumptions!B47 -> 554.4 | C4: 22% drawdown from $471 ATH
A5: Implied Upside from Current ($366): | B5: =Assumptions!B48 -> 0.5147541
A7: VARIANT PERCEPTION (Where We Differ from Consensus)
A8: 1.
A9: 2.
A10: 3.
A12: SCENARIO SUMMARY
A13: AI SUPERCYCLE (25%)
A14: Supply constraints persist beyond CY2027. HBM TAM exceeds $1...
A15: STEADY GROWTH — BASE (45%)
A16: Orderly normalization. GM settles at 60-65%. HBM grows at pl...
A17: CYCLICAL CORRECTION (20%)
A18: Hyperscaler capex plateaus. Pricing normalizes faster. Samsu...
A19: HARD LANDING (10%)
... A62: FQ3 FCF doubling
